<?xml version="1.0"?>
<games season="2014" type="REG" week="12" xmlns="http://feed.elasticstats.com/schema/nfl/boxscore-v1.0.xsd"><!--Generation started at 2015-06-29 15:05:29 +0000-->  <game away="TB" clock=":00" completed="2014-11-23T21:19:41+00:00" home="CHI" id="c2b22b91-c200-4760-84b7-46c47b96c5f7" quarter="4" scheduled="2014-11-23T18:00:00+00:00" status="closed">
    <team id="CHI" market="Chicago" name="Bears" remaining_challenges="2" remaining_timeouts="2">
      <scoring points="21">
        <quarter number="1" points="0"/>
        <quarter number="2" points="0"/>
        <quarter number="3" points="21"/>
        <quarter number="4" points="0"/>
      </scoring>
    </team>
    <team id="TB" market="Tampa Bay" name="Buccaneers" remaining_challenges="1" remaining_timeouts="2">
      <scoring points="13">
        <quarter number="1" points="0"/>
        <quarter number="2" points="10"/>
        <quarter number="3" points="0"/>
        <quarter number="4" points="3"/>
      </scoring>
    </team>
    <scoring_drives>
      <drive clock="01:39" quarter="1" sequence="1" team="TB">
        <score clock="13:32" points="6" quarter="2" type="touchdown">
          <summary><![CDATA[12-J.McCown complete to 13-M.Evans. 13-M.Evans runs 19 yards for a touchdown.]]></summary>
          <links>
            <link href="/2014/REG/12/TB/CHI/plays/22905de4-8f17-40e5-aedf-e23d52e096b0.xml" rel="summary" type="application/xml"/>
          </links>
        </score>
        <score clock="13:24" points="1" quarter="2" type="extrapoint">
          <summary><![CDATA[7-P.Murray extra point is good.]]></summary>
          <links>
            <link href="/2014/REG/12/TB/CHI/plays/2ae41451-fa0b-4cde-a357-64ed8bb8ba18.xml" rel="summary" type="application/xml"/>
          </links>
        </score>
      </drive>
      <drive clock="01:48" quarter="2" sequence="2" team="TB">
        <score clock=":09" points="3" quarter="2" type="fieldgoal">
          <summary><![CDATA[7-P.Murray 32 yards Field Goal is Good.]]></summary>
          <links>
            <link href="/2014/REG/12/TB/CHI/plays/ab61b4bd-c502-4f34-93ba-80bc500aee55.xml" rel="summary" type="application/xml"/>
          </links>
        </score>
      </drive>
      <drive clock="14:01" quarter="3" sequence="3" team="CHI">
        <score clock="10:39" points="6" quarter="3" type="touchdown">
          <summary><![CDATA[6-J.Cutler complete to 17-A.Jeffery. 17-A.Jeffery runs 2 yards for a touchdown.]]></summary>
          <links>
            <link href="/2014/REG/12/TB/CHI/plays/0a03a58a-8655-4eb1-b4c0-ae47f02e5037.xml" rel="summary" type="application/xml"/>
          </links>
        </score>
        <score clock="10:33" points="1" quarter="3" type="extrapoint">
          <summary><![CDATA[9-R.Gould extra point is good.]]></summary>
          <links>
            <link href="/2014/REG/12/TB/CHI/plays/957806db-c14d-4786-a9e3-bada166917db.xml" rel="summary" type="application/xml"/>
          </links>
        </score>
      </drive>
      <drive clock="04:57" quarter="3" sequence="4" team="CHI">
        <score clock="04:57" points="6" quarter="3" type="touchdown">
          <summary><![CDATA[22-M.Forte runs 13 yards for a touchdown.]]></summary>
          <links>
            <link href="/2014/REG/12/TB/CHI/plays/9931dc79-059c-4f94-bc07-9a133e7858bf.xml" rel="summary" type="application/xml"/>
          </links>
        </score>
        <score clock="04:51" points="1" quarter="3" type="extrapoint">
          <summary><![CDATA[9-R.Gould extra point is good.]]></summary>
          <links>
            <link href="/2014/REG/12/TB/CHI/plays/bc4443d1-0c55-4f2b-b64d-89aefb7302ea.xml" rel="summary" type="application/xml"/>
          </links>
        </score>
      </drive>
      <drive clock="04:38" quarter="3" sequence="5" team="CHI">
        <score clock="03:09" points="6" quarter="3" type="touchdown">
          <summary><![CDATA[22-M.Forte runs 1 yard for a touchdown.]]></summary>
          <links>
            <link href="/2014/REG/12/TB/CHI/plays/136b7312-719a-42bd-9eca-9d49c6ee965d.xml" rel="summary" type="application/xml"/>
          </links>
        </score>
        <score clock="03:02" points="1" quarter="3" type="extrapoint">
          <summary><![CDATA[9-R.Gould extra point is good.]]></summary>
          <links>
            <link href="/2014/REG/12/TB/CHI/plays/92cbaed9-87cd-4f2e-b325-88d734fce223.xml" rel="summary" type="application/xml"/>
          </links>
        </score>
      </drive>
      <drive clock="07:51" quarter="4" sequence="6" team="TB">
        <score clock="05:01" points="3" quarter="4" type="fieldgoal">
          <summary><![CDATA[7-P.Murray 39 yards Field Goal is Good.]]></summary>
          <links>
            <link href="/2014/REG/12/TB/CHI/plays/48b95280-858c-41c3-8d78-9d0d035ea695.xml" rel="summary" type="application/xml"/>
          </links>
        </score>
      </drive>
    </scoring_drives>
  </game>
  <game away="MIA" clock=":00" completed="2014-11-24T00:36:00+00:00" home="DEN" id="a131287d-9b9d-4e1b-9d0c-473c46bf3f32" quarter="4" scheduled="2014-11-23T21:25:00+00:00" status="closed">
    <team id="DEN" market="Denver" name="Broncos" remaining_challenges="1" remaining_timeouts="2">
      <scoring points="39">
        <quarter number="1" points="3"/>
        <quarter number="2" points="14"/>
        <quarter number="3" points="0"/>
        <quarter number="4" points="22"/>
      </scoring>
    </team>
    <team id="MIA" market="Miami" name="Dolphins" remaining_challenges="2" remaining_timeouts="2">
      <scoring points="36">
        <quarter number="1" points="7"/>
        <quarter number="2" points="14"/>
        <quarter number="3" points="7"/>
        <quarter number="4" points="8"/>
      </scoring>
    </team>
    <scoring_drives>
      <drive clock="15:00" quarter="1" sequence="1" team="MIA">
        <score clock="11:25" points="6" quarter="1" type="touchdown">
          <summary><![CDATA[30-D.Thomas runs 3 yards for a touchdown.]]></summary>
          <links>
            <link href="/2014/REG/12/MIA/DEN/plays/dae26e7c-2276-4b91-8ae2-31cbd3b17d70.xml" rel="summary" type="application/xml"/>
          </links>
        </score>
        <score clock="11:22" points="1" quarter="1" type="extrapoint">
          <summary><![CDATA[9-C.Sturgis extra point is good.]]></summary>
          <links>
            <link href="/2014/REG/12/MIA/DEN/plays/1b0c3ae8-30c6-4410-8ae5-b4907bcf6533.xml" rel="summary" type="application/xml"/>
          </links>
        </score>
      </drive>
      <drive clock="11:22" quarter="1" sequence="2" team="DEN">
        <score clock="04:14" points="3" quarter="1" type="fieldgoal">
          <summary><![CDATA[8-B.McManus 38 yards Field Goal is Good.]]></summary>
          <links>
            <link href="/2014/REG/12/MIA/DEN/plays/1ae0f597-4d0c-4bbe-b185-9c2a9ccbcad3.xml" rel="summary" type="application/xml"/>
          </links>
        </score>
      </drive>
      <drive clock="01:40" quarter="1" sequence="3" team="MIA">
        <score clock="12:58" points="6" quarter="2" type="touchdown">
          <summary><![CDATA[17-R.Tannehill runs 1 yard for a touchdown.]]></summary>
          <links>
            <link href="/2014/REG/12/MIA/DEN/plays/76701eda-5cab-4a76-91a4-eb30aeea3722.xml" rel="summary" type="application/xml"/>
          </links>
        </score>
        <score clock="12:53" points="1" quarter="2" type="extrapoint">
          <summary><![CDATA[9-C.Sturgis extra point is good.]]></summary>
          <links>
            <link href="/2014/REG/12/MIA/DEN/plays/bc9baff0-d1d7-4c09-85bd-b81c362f61a6.xml" rel="summary" type="application/xml"/>
          </links>
        </score>
      </drive>
      <drive clock="12:53" quarter="2" sequence="4" team="DEN">
        <score clock="07:13" points="6" quarter="2" type="touchdown">
          <summary><![CDATA[18-P.Manning complete to 88-D.Thomas. 88-D.Thomas runs 5 yards for a touchdown.]]></summary>
          <links>
            <link href="/2014/REG/12/MIA/DEN/plays/46497ab0-0065-4c74-b967-9f0e909c98cf.xml" rel="summary" type="application/xml"/>
          </links>
        </score>
        <score clock="07:08" points="1" quarter="2" type="extrapoint">
          <summary><![CDATA[8-B.McManus extra point is good.]]></summary>
          <links>
            <link href="/2014/REG/12/MIA/DEN/plays/431874aa-f1ab-42c2-baff-2efc7ace7aa6.xml" rel="summary" type="application/xml"/>
          </links>
        </score>
      </drive>
      <drive clock="07:08" quarter="2" sequence="5" team="MIA">
        <score clock="02:00" points="6" quarter="2" type="touchdown">
          <summary><![CDATA[17-R.Tannehill complete to 11-M.Wallace. 11-M.Wallace runs 10 yards for a touchdown.]]></summary>
          <links>
            <link href="/2014/REG/12/MIA/DEN/plays/6a8669bb-8f4e-4f14-9ce1-fd981d3e5884.xml" rel="summary" type="application/xml"/>
          </links>
        </score>
        <score clock="01:54" points="1" quarter="2" type="extrapoint">
          <summary><![CDATA[9-C.Sturgis extra point is good.]]></summary>
          <links>
            <link href="/2014/REG/12/MIA/DEN/plays/7a9bffef-a89a-4494-9761-62a3e5730d55.xml" rel="summary" type="application/xml"/>
          </links>
        </score>
      </drive>
      <drive clock="01:54" quarter="2" sequence="6" team="DEN">
        <score clock=":16" points="6" quarter="2" type="touchdown">
          <summary><![CDATA[18-P.Manning complete to 88-D.Thomas. 88-D.Thomas runs 14 yards for a touchdown.]]></summary>
          <links>
            <link href="/2014/REG/12/MIA/DEN/plays/6e2cce83-b94a-4da0-8e53-88ab8aa6842e.xml" rel="summary" type="application/xml"/>
          </links>
        </score>
        <score clock=":12" points="1" quarter="2" type="extrapoint">
          <summary><![CDATA[8-B.McManus extra point is good.]]></summary>
          <links>
            <link href="/2014/REG/12/MIA/DEN/plays/37511b11-dc33-4e29-9db8-8e3b36746c17.xml" rel="summary" type="application/xml"/>
          </links>
        </score>
      </drive>
      <drive clock="08:06" quarter="3" sequence="7" team="MIA">
        <score clock="02:15" points="6" quarter="3" type="touchdown">
          <summary><![CDATA[17-R.Tannehill complete to 14-J.Landry. 14-J.Landry runs 5 yards for a touchdown.]]></summary>
          <links>
            <link href="/2014/REG/12/MIA/DEN/plays/3add3d19-edef-42f4-9a05-38a070ed03fe.xml" rel="summary" type="application/xml"/>
          </links>
        </score>
        <score clock="02:11" points="1" quarter="3" type="extrapoint">
          <summary><![CDATA[9-C.Sturgis extra point is good.]]></summary>
          <links>
            <link href="/2014/REG/12/MIA/DEN/plays/645af77d-58c2-4dd7-898a-16d8fe946aa8.xml" rel="summary" type="application/xml"/>
          </links>
        </score>
      </drive>
      <drive clock="02:11" quarter="3" sequence="8" team="DEN">
        <score clock="14:14" points="6" quarter="4" type="touchdown">
          <summary><![CDATA[18-P.Manning complete to 88-D.Thomas. 88-D.Thomas runs 5 yards for a touchdown.]]></summary>
          <links>
            <link href="/2014/REG/12/MIA/DEN/plays/6b8b441a-af73-4b62-8d05-e1f535944820.xml" rel="summary" type="application/xml"/>
          </links>
        </score>
        <score clock="14:09" points="2" quarter="4" type="conversion">
          <summary><![CDATA[18-P.Manning complete to 10-E.Sanders. 10-E.Sanders to MIA End Zone for 2 yards. Conversion is good.]]></summary>
          <links>
            <link href="/2014/REG/12/MIA/DEN/plays/48481cbe-d4e4-4c7b-8e73-0e5fea80c8bd.xml" rel="summary" type="application/xml"/>
          </links>
        </score>
      </drive>
      <drive clock="11:17" quarter="4" sequence="9" team="DEN">
        <score clock="05:05" points="6" quarter="4" type="touchdown">
          <summary><![CDATA[22-C.Anderson runs 10 yards for a touchdown.]]></summary>
          <links>
            <link href="/2014/REG/12/MIA/DEN/plays/42260372-f3d4-4b45-9189-0c5fbf6dc33c.xml" rel="summary" type="application/xml"/>
          </links>
        </score>
        <score clock="05:01" points="1" quarter="4" type="extrapoint">
          <summary><![CDATA[8-B.McManus extra point is good.]]></summary>
          <links>
            <link href="/2014/REG/12/MIA/DEN/plays/d38adb5a-c1cb-409b-b615-940f05753de1.xml" rel="summary" type="application/xml"/>
          </links>
        </score>
      </drive>
      <drive clock="03:30" quarter="4" sequence="10" team="DEN">
        <score clock="03:17" points="6" quarter="4" type="touchdown">
          <summary><![CDATA[18-P.Manning complete to 83-W.Welker. 83-W.Welker runs 2 yards for a touchdown.]]></summary>
          <links>
            <link href="/2014/REG/12/MIA/DEN/plays/c57dd387-f331-4a6c-8c1a-81301a1ee1d6.xml" rel="summary" type="application/xml"/>
          </links>
        </score>
        <score clock="03:13" points="1" quarter="4" type="extrapoint">
          <summary><![CDATA[8-B.McManus extra point is good.]]></summary>
          <links>
            <link href="/2014/REG/12/MIA/DEN/plays/b37b0f8f-d3cb-4725-a620-c2af9d3a1832.xml" rel="summary" type="application/xml"/>
          </links>
        </score>
      </drive>
      <drive clock="03:13" quarter="4" sequence="11" team="MIA">
        <score clock="01:37" points="6" quarter="4" type="touchdown">
          <summary><![CDATA[17-R.Tannehill complete to 14-J.Landry. 14-J.Landry runs 1 yard for a touchdown.]]></summary>
          <links>
            <link href="/2014/REG/12/MIA/DEN/plays/e0673996-b97a-41bf-8c98-ecfc35103d0d.xml" rel="summary" type="application/xml"/>
          </links>
        </score>
        <score clock="01:34" points="2" quarter="4" type="conversion">
          <summary><![CDATA[30-D.Thomas to DEN End Zone for 1 yard. Conversion is good.]]></summary>
          <links>
            <link href="/2014/REG/12/MIA/DEN/plays/2b26261d-168b-4f56-bfa0-3fdfcf34e8cf.xml" rel="summary" type="application/xml"/>
          </links>
        </score>
      </drive>
    </scoring_drives>
  </game>
  <game away="NYJ" clock=":00" completed="2014-11-25T02:56:18+00:00" home="BUF" id="b7e761e1-0bf7-4512-a54e-aec734935e5c" quarter="4" scheduled="2014-11-25T00:00:00+00:00" status="closed">
    <team id="BUF" market="Buffalo" name="Bills" remaining_challenges="1" remaining_timeouts="2">
      <scoring points="38">
        <quarter number="1" points="7"/>
        <quarter number="2" points="7"/>
        <quarter number="3" points="17"/>
        <quarter number="4" points="7"/>
      </scoring>
    </team>
    <team id="NYJ" market="New York" name="Jets" remaining_challenges="2" remaining_timeouts="2">
      <scoring points="3">
        <quarter number="1" points="3"/>
        <quarter number="2" points="0"/>
        <quarter number="3" points="0"/>
        <quarter number="4" points="0"/>
      </scoring>
    </team>
    <scoring_drives>
      <drive clock="13:21" quarter="1" sequence="1" team="BUF">
        <score clock="08:09" points="6" quarter="1" type="touchdown">
          <summary><![CDATA[18-K.Orton complete to 10-R.Woods. 10-R.Woods runs 7 yards for a touchdown.]]></summary>
          <links>
            <link href="/2014/REG/12/NYJ/BUF/plays/b92cde2c-fcba-4558-ab9c-fb1fd7da504b.xml" rel="summary" type="application/xml"/>
          </links>
        </score>
        <score clock="08:04" points="1" quarter="1" type="extrapoint">
          <summary><![CDATA[2-D.Carpenter extra point is good.]]></summary>
          <links>
            <link href="/2014/REG/12/NYJ/BUF/plays/6503d11e-90c9-4265-b3bf-9c54bee65eb3.xml" rel="summary" type="application/xml"/>
          </links>
        </score>
      </drive>
      <drive clock="05:17" quarter="1" sequence="2" team="NYJ">
        <score clock="01:05" points="3" quarter="1" type="fieldgoal">
          <summary><![CDATA[2-N.Folk 27 yards Field Goal is Good.]]></summary>
          <links>
            <link href="/2014/REG/12/NYJ/BUF/plays/9cfb6d23-f1d4-4918-95b7-2c4af5af6f20.xml" rel="summary" type="application/xml"/>
          </links>
        </score>
      </drive>
      <drive clock="05:47" quarter="2" sequence="3" team="BUF">
        <score clock=":48" points="6" quarter="2" type="touchdown">
          <summary><![CDATA[18-K.Orton complete to 84-S.Chandler. 84-S.Chandler runs 19 yards for a touchdown.]]></summary>
          <links>
            <link href="/2014/REG/12/NYJ/BUF/plays/2821a726-0e01-4789-b3bc-42b38e8325bb.xml" rel="summary" type="application/xml"/>
          </links>
        </score>
        <score clock=":43" points="1" quarter="2" type="extrapoint">
          <summary><![CDATA[2-D.Carpenter extra point is good.]]></summary>
          <links>
            <link href="/2014/REG/12/NYJ/BUF/plays/6b9b5f5a-7a14-4a7b-9304-c166c73b2aaf.xml" rel="summary" type="application/xml"/>
          </links>
        </score>
      </drive>
      <drive clock="15:00" quarter="3" sequence="4" team="BUF">
        <score clock="09:50" points="3" quarter="3" type="fieldgoal">
          <summary><![CDATA[2-D.Carpenter 53 yards Field Goal is Good.]]></summary>
          <links>
            <link href="/2014/REG/12/NYJ/BUF/plays/d6b44d31-9221-40a6-86a9-6b5caa9b88a5.xml" rel="summary" type="application/xml"/>
          </links>
        </score>
      </drive>
      <drive clock="09:45" quarter="3" sequence="5" team="NYJ">
        <score clock="08:05" points="6" quarter="3" type="touchdown">
          <summary><![CDATA[4-R.Quigley punts -10 yards from NYJ 10 blocked by 26-A.Dixon. 91-M.Lawson runs no gain for a touchdown.]]></summary>
          <links>
            <link href="/2014/REG/12/NYJ/BUF/plays/a3338a1a-9f16-4e93-9e4e-11e97272bf1d.xml" rel="summary" type="application/xml"/>
          </links>
        </score>
      </drive>
      <drive clock="07:57" quarter="3" sequence="6" team="BUF">
        <score clock="07:57" points="1" quarter="3" type="extrapoint">
          <summary><![CDATA[2-D.Carpenter extra point is good.]]></summary>
          <links>
            <link href="/2014/REG/12/NYJ/BUF/plays/4641c403-3363-4844-b019-d6e0bfce2084.xml" rel="summary" type="application/xml"/>
          </links>
        </score>
      </drive>
      <drive clock="05:52" quarter="3" sequence="7" team="BUF">
        <score clock="05:09" points="6" quarter="3" type="touchdown">
          <summary><![CDATA[22-F.Jackson runs 5 yards for a touchdown.]]></summary>
          <links>
            <link href="/2014/REG/12/NYJ/BUF/plays/71a78583-4def-4ebc-9053-40335923cb40.xml" rel="summary" type="application/xml"/>
          </links>
        </score>
        <score clock="05:03" points="1" quarter="3" type="extrapoint">
          <summary><![CDATA[2-D.Carpenter extra point is good.]]></summary>
          <links>
            <link href="/2014/REG/12/NYJ/BUF/plays/e3894221-ae28-49cd-9db5-08058cc20042.xml" rel="summary" type="application/xml"/>
          </links>
        </score>
      </drive>
      <drive clock="10:05" quarter="4" sequence="8" team="BUF">
        <score clock="06:00" points="6" quarter="4" type="touchdown">
          <summary><![CDATA[26-A.Dixon runs 30 yards for a touchdown.]]></summary>
          <links>
            <link href="/2014/REG/12/NYJ/BUF/plays/9434cf6a-5f1a-4283-8148-b78cde60754d.xml" rel="summary" type="application/xml"/>
          </links>
        </score>
        <score clock="05:53" points="1" quarter="4" type="extrapoint">
          <summary><![CDATA[2-D.Carpenter extra point is good.]]></summary>
          <links>
            <link href="/2014/REG/12/NYJ/BUF/plays/f9cd8209-cd23-4b48-92cc-400d5ca5ea26.xml" rel="summary" type="application/xml"/>
          </links>
        </score>
      </drive>
    </scoring_drives>
  </game>
  <game away="WAS" clock=":00" completed="2014-11-24T00:21:43+00:00" home="SF" id="46bbaa65-4fee-490d-a39c-2b0482e7e0cb" quarter="4" scheduled="2014-11-23T21:25:00+00:00" status="closed">
    <team id="SF" market="San Francisco" name="49ers" remaining_challenges="2" remaining_timeouts="2">
      <scoring points="17">
        <quarter number="1" points="7"/>
        <quarter number="2" points="3"/>
        <quarter number="3" points="0"/>
        <quarter number="4" points="7"/>
      </scoring>
    </team>
    <team id="WAS" market="Washington" name="Redskins" remaining_challenges="1" remaining_timeouts="2">
      <scoring points="13">
        <quarter number="1" points="0"/>
        <quarter number="2" points="7"/>
        <quarter number="3" points="3"/>
        <quarter number="4" points="3"/>
      </scoring>
    </team>
    <scoring_drives>
      <drive clock="13:31" quarter="1" sequence="1" team="SF">
        <score clock="11:20" points="6" quarter="1" type="touchdown">
          <summary><![CDATA[7-C.Kaepernick complete to 81-A.Boldin. 81-A.Boldin runs 30 yards for a touchdown.]]></summary>
          <links>
            <link href="/2014/REG/12/WAS/SF/plays/88fec3c7-a570-40c3-8c76-e36110e0e4e8.xml" rel="summary" type="application/xml"/>
          </links>
        </score>
        <score clock="11:13" points="1" quarter="1" type="extrapoint">
          <summary><![CDATA[9-P.Dawson extra point is good.]]></summary>
          <links>
            <link href="/2014/REG/12/WAS/SF/plays/3a903da8-4f2b-45ee-abc7-43b1ff8c8622.xml" rel="summary" type="application/xml"/>
          </links>
        </score>
      </drive>
      <drive clock="11:21" quarter="2" sequence="2" team="WAS">
        <score clock="05:38" points="6" quarter="2" type="touchdown">
          <summary><![CDATA[46-A.Morris runs 1 yard for a touchdown.]]></summary>
          <links>
            <link href="/2014/REG/12/WAS/SF/plays/5b430832-43d5-4ba9-88c1-52a31a3c2b43.xml" rel="summary" type="application/xml"/>
          </links>
        </score>
        <score clock="05:33" points="1" quarter="2" type="extrapoint">
          <summary><![CDATA[2-K.Forbath extra point is good.]]></summary>
          <links>
            <link href="/2014/REG/12/WAS/SF/plays/ac58692c-3c53-4ac1-a71c-6682eca950c8.xml" rel="summary" type="application/xml"/>
          </links>
        </score>
      </drive>
      <drive clock="05:33" quarter="2" sequence="3" team="SF">
        <score clock=":05" points="3" quarter="2" type="fieldgoal">
          <summary><![CDATA[9-P.Dawson 41 yards Field Goal is Good.]]></summary>
          <links>
            <link href="/2014/REG/12/WAS/SF/plays/a4a40af6-a354-484a-8636-97e696c314d0.xml" rel="summary" type="application/xml"/>
          </links>
        </score>
      </drive>
      <drive clock="04:49" quarter="3" sequence="4" team="WAS">
        <score clock=":35" points="3" quarter="3" type="fieldgoal">
          <summary><![CDATA[2-K.Forbath 27 yards Field Goal is Good.]]></summary>
          <links>
            <link href="/2014/REG/12/WAS/SF/plays/596e1017-1425-4461-af34-94b65db99d9d.xml" rel="summary" type="application/xml"/>
          </links>
        </score>
      </drive>
      <drive clock="10:03" quarter="4" sequence="5" team="WAS">
        <score clock="07:48" points="3" quarter="4" type="fieldgoal">
          <summary><![CDATA[2-K.Forbath 46 yards Field Goal is Good.]]></summary>
          <links>
            <link href="/2014/REG/12/WAS/SF/plays/1516faf5-c9ae-4000-a275-1930084c3300.xml" rel="summary" type="application/xml"/>
          </links>
        </score>
      </drive>
      <drive clock="07:42" quarter="4" sequence="6" team="SF">
        <score clock="03:04" points="6" quarter="4" type="touchdown">
          <summary><![CDATA[28-C.Hyde runs 4 yards for a touchdown.]]></summary>
          <links>
            <link href="/2014/REG/12/WAS/SF/plays/c848f6bf-eeea-486c-be95-409b96c38248.xml" rel="summary" type="application/xml"/>
          </links>
        </score>
        <score clock="02:59" points="1" quarter="4" type="extrapoint">
          <summary><![CDATA[9-P.Dawson extra point is good.]]></summary>
          <links>
            <link href="/2014/REG/12/WAS/SF/plays/ca599c41-ac79-4903-ac29-8d3d27bb5b4c.xml" rel="summary" type="application/xml"/>
          </links>
        </score>
      </drive>
    </scoring_drives>
  </game>
  <game away="CLE" clock=":00" completed="2014-11-23T21:08:22+00:00" home="ATL" id="6642126e-b3a8-42f8-951b-6aee5b5350ad" quarter="4" scheduled="2014-11-23T18:00:00+00:00" status="closed">
    <team id="ATL" market="Atlanta" name="Falcons" remaining_challenges="2" remaining_timeouts="2">
      <scoring points="24">
        <quarter number="1" points="7"/>
        <quarter number="2" points="7"/>
        <quarter number="3" points="0"/>
        <quarter number="4" points="10"/>
      </scoring>
    </team>
    <team id="CLE" market="Cleveland" name="Browns" remaining_challenges="2" remaining_timeouts="2">
      <scoring points="26">
        <quarter number="1" points="7"/>
        <quarter number="2" points="6"/>
        <quarter number="3" points="10"/>
        <quarter number="4" points="3"/>
      </scoring>
    </team>
    <scoring_drives>
      <drive clock="10:19" quarter="1" sequence="1" team="ATL">
        <score clock="05:59" points="6" quarter="1" type="touchdown">
          <summary><![CDATA[2-M.Ryan complete to 11-J.Jones. 11-J.Jones runs 24 yards for a touchdown.]]></summary>
          <links>
            <link href="/2014/REG/12/CLE/ATL/plays/9451cdcd-6023-4161-9286-77d7a6d1223f.xml" rel="summary" type="application/xml"/>
          </links>
        </score>
        <score clock="05:53" points="1" quarter="1" type="extrapoint">
          <summary><![CDATA[3-M.Bryant extra point is good.]]></summary>
          <links>
            <link href="/2014/REG/12/CLE/ATL/plays/9178b9fd-6521-4201-b452-58413fc72da6.xml" rel="summary" type="application/xml"/>
          </links>
        </score>
      </drive>
      <drive clock="05:53" quarter="1" sequence="2" team="CLE">
        <score clock="01:40" points="6" quarter="1" type="touchdown">
          <summary><![CDATA[34-I.Crowell runs 11 yards for a touchdown.]]></summary>
          <links>
            <link href="/2014/REG/12/CLE/ATL/plays/5c662d0e-5b2d-4e83-b741-69182143c221.xml" rel="summary" type="application/xml"/>
          </links>
        </score>
        <score clock="01:33" points="1" quarter="1" type="extrapoint">
          <summary><![CDATA[8-B.Cundiff extra point is good.]]></summary>
          <links>
            <link href="/2014/REG/12/CLE/ATL/plays/09399d87-03bc-49b7-8cb9-9edfb9ba69a1.xml" rel="summary" type="application/xml"/>
          </links>
        </score>
      </drive>
      <drive clock="14:54" quarter="2" sequence="3" team="CLE">
        <score clock="13:22" points="3" quarter="2" type="fieldgoal">
          <summary><![CDATA[8-B.Cundiff 33 yards Field Goal is Good.]]></summary>
          <links>
            <link href="/2014/REG/12/CLE/ATL/plays/1924da49-d7b7-414d-98b5-26717f4c5a58.xml" rel="summary" type="application/xml"/>
          </links>
        </score>
      </drive>
      <drive clock="11:15" quarter="2" sequence="4" team="CLE">
        <score clock="09:26" points="3" quarter="2" type="fieldgoal">
          <summary><![CDATA[8-B.Cundiff 37 yards Field Goal is Good.]]></summary>
          <links>
            <link href="/2014/REG/12/CLE/ATL/plays/dd8a015a-d68a-4d9a-9132-ca915513e044.xml" rel="summary" type="application/xml"/>
          </links>
        </score>
      </drive>
      <drive clock="02:52" quarter="2" sequence="5" team="ATL">
        <score clock="01:00" points="6" quarter="2" type="touchdown">
          <summary><![CDATA[2-M.Ryan complete to 32-J.Rodgers. 32-J.Rodgers runs 8 yards for a touchdown.]]></summary>
          <links>
            <link href="/2014/REG/12/CLE/ATL/plays/af8ad980-9f2d-4f84-acd4-d63337dcbde3.xml" rel="summary" type="application/xml"/>
          </links>
        </score>
        <score clock=":55" points="1" quarter="2" type="extrapoint">
          <summary><![CDATA[3-M.Bryant extra point is good.]]></summary>
          <links>
            <link href="/2014/REG/12/CLE/ATL/plays/97341365-6938-4abc-8570-a9630ca68a5f.xml" rel="summary" type="application/xml"/>
          </links>
        </score>
      </drive>
      <drive clock="15:00" quarter="3" sequence="6" team="CLE">
        <score clock="09:51" points="3" quarter="3" type="fieldgoal">
          <summary><![CDATA[8-B.Cundiff 32 yards Field Goal is Good.]]></summary>
          <links>
            <link href="/2014/REG/12/CLE/ATL/plays/c2dca929-7306-4cd1-a319-4edf1518ac87.xml" rel="summary" type="application/xml"/>
          </links>
        </score>
      </drive>
      <drive clock="05:44" quarter="3" sequence="7" team="CLE">
        <score clock=":59" points="6" quarter="3" type="touchdown">
          <summary><![CDATA[34-I.Crowell runs 26 yards for a touchdown.]]></summary>
          <links>
            <link href="/2014/REG/12/CLE/ATL/plays/d660caf3-9844-4eb7-b2af-7ccd09986738.xml" rel="summary" type="application/xml"/>
          </links>
        </score>
        <score clock=":46" points="1" quarter="3" type="extrapoint">
          <summary><![CDATA[8-B.Cundiff extra point is good.]]></summary>
          <links>
            <link href="/2014/REG/12/CLE/ATL/plays/33a7c52e-a9ac-4e78-9673-4d71de25e753.xml" rel="summary" type="application/xml"/>
          </links>
        </score>
      </drive>
      <drive clock=":46" quarter="3" sequence="8" team="ATL">
        <score clock="09:36" points="6" quarter="4" type="touchdown">
          <summary><![CDATA[39-S.Jackson runs 1 yard for a touchdown.]]></summary>
          <links>
            <link href="/2014/REG/12/CLE/ATL/plays/c4cd3d73-080a-42cc-b0e0-943f4d3f3723.xml" rel="summary" type="application/xml"/>
          </links>
        </score>
        <score clock="09:31" points="1" quarter="4" type="extrapoint">
          <summary><![CDATA[3-M.Bryant extra point is good.]]></summary>
          <links>
            <link href="/2014/REG/12/CLE/ATL/plays/3fc34f38-3448-471e-a467-8be6e6c09ff1.xml" rel="summary" type="application/xml"/>
          </links>
        </score>
      </drive>
      <drive clock="02:42" quarter="4" sequence="9" team="ATL">
        <score clock=":49" points="3" quarter="4" type="fieldgoal">
          <summary><![CDATA[3-M.Bryant 53 yards Field Goal is Good.]]></summary>
          <links>
            <link href="/2014/REG/12/CLE/ATL/plays/6a7125b5-f961-4de6-a801-3014f7c9b417.xml" rel="summary" type="application/xml"/>
          </links>
        </score>
      </drive>
      <drive clock=":44" quarter="4" sequence="10" team="CLE">
        <score clock=":05" points="3" quarter="4" type="fieldgoal">
          <summary><![CDATA[8-B.Cundiff 37 yards Field Goal is Good.]]></summary>
          <links>
            <link href="/2014/REG/12/CLE/ATL/plays/3606c945-d16b-4569-8514-115899e43499.xml" rel="summary" type="application/xml"/>
          </links>
        </score>
      </drive>
    </scoring_drives>
  </game>
  <game away="TEN" clock=":00" completed="2014-11-23T21:36:51+00:00" home="PHI" id="4e10ba74-53b8-475f-a50b-aa022883b822" quarter="4" scheduled="2014-11-23T18:00:00+00:00" status="closed">
    <team id="PHI" market="Philadelphia" name="Eagles" remaining_challenges="1" remaining_timeouts="2">
      <scoring points="43">
        <quarter number="1" points="17"/>
        <quarter number="2" points="10"/>
        <quarter number="3" points="7"/>
        <quarter number="4" points="9"/>
      </scoring>
    </team>
    <team id="TEN" market="Tennessee" name="Titans" remaining_challenges="2" remaining_timeouts="2">
      <scoring points="24">
        <quarter number="1" points="0"/>
        <quarter number="2" points="17"/>
        <quarter number="3" points="0"/>
        <quarter number="4" points="7"/>
      </scoring>
    </team>
    <scoring_drives>
      <drive clock="15:00" quarter="1" sequence="1" team="PHI">
        <score clock="15:00" points="6" quarter="1" type="touchdown">
          <summary><![CDATA[8-R.Succop kicks 72 yards from TEN 35. 11-J.Huff runs 107 yards for a touchdown.]]></summary>
          <links>
            <link href="/2014/REG/12/TEN/PHI/plays/be03e816-3fb9-462c-a9a2-ed7d1fca3f35.xml" rel="summary" type="application/xml"/>
          </links>
        </score>
        <score clock="14:47" points="1" quarter="1" type="extrapoint">
          <summary><![CDATA[1-C.Parkey extra point is good.]]></summary>
          <links>
            <link href="/2014/REG/12/TEN/PHI/plays/9eda01fe-7fc5-40b6-88f3-e643971fd413.xml" rel="summary" type="application/xml"/>
          </links>
        </score>
      </drive>
      <drive clock="13:37" quarter="1" sequence="2" team="PHI">
        <score clock="10:50" points="6" quarter="1" type="touchdown">
          <summary><![CDATA[43-D.Sproles runs 4 yards for a touchdown.]]></summary>
          <links>
            <link href="/2014/REG/12/TEN/PHI/plays/6c907356-3089-4d18-800a-60619ac8900d.xml" rel="summary" type="application/xml"/>
          </links>
        </score>
        <score clock="10:44" points="1" quarter="1" type="extrapoint">
          <summary><![CDATA[1-C.Parkey extra point is good.]]></summary>
          <links>
            <link href="/2014/REG/12/TEN/PHI/plays/e29d94ce-35e0-4bff-acd4-4c304a540565.xml" rel="summary" type="application/xml"/>
          </links>
        </score>
      </drive>
      <drive clock="06:18" quarter="1" sequence="3" team="PHI">
        <score clock="03:29" points="3" quarter="1" type="fieldgoal">
          <summary><![CDATA[1-C.Parkey 36 yards Field Goal is Good.]]></summary>
          <links>
            <link href="/2014/REG/12/TEN/PHI/plays/8a42a012-117c-4278-951e-d6f4695b9ea5.xml" rel="summary" type="application/xml"/>
          </links>
        </score>
      </drive>
      <drive clock=":30" quarter="1" sequence="4" team="TEN">
        <score clock="15:00" points="6" quarter="2" type="touchdown">
          <summary><![CDATA[7-Z.Mettenberger complete to 15-J.Hunter. 15-J.Hunter runs 40 yards for a touchdown.]]></summary>
          <links>
            <link href="/2014/REG/12/TEN/PHI/plays/cf1ccb43-e8c5-4a47-a98a-2657bb45fd53.xml" rel="summary" type="application/xml"/>
          </links>
        </score>
        <score clock="14:51" points="1" quarter="2" type="extrapoint">
          <summary><![CDATA[8-R.Succop extra point is good.]]></summary>
          <links>
            <link href="/2014/REG/12/TEN/PHI/plays/1e26dd73-2553-4543-b2b5-3fea0c74b702.xml" rel="summary" type="application/xml"/>
          </links>
        </score>
      </drive>
      <drive clock="14:51" quarter="2" sequence="5" team="PHI">
        <score clock="11:33" points="3" quarter="2" type="fieldgoal">
          <summary><![CDATA[1-C.Parkey 26 yards Field Goal is Good.]]></summary>
          <links>
            <link href="/2014/REG/12/TEN/PHI/plays/c38ee495-2418-44e1-a973-92e1d72f5f40.xml" rel="summary" type="application/xml"/>
          </links>
        </score>
      </drive>
      <drive clock="11:29" quarter="2" sequence="6" team="TEN">
        <score clock="08:24" points="6" quarter="2" type="touchdown">
          <summary><![CDATA[23-S.Greene runs 2 yards for a touchdown.]]></summary>
          <links>
            <link href="/2014/REG/12/TEN/PHI/plays/e36defd8-8073-4dee-96f0-359dde5cb169.xml" rel="summary" type="application/xml"/>
          </links>
        </score>
        <score clock="08:22" points="1" quarter="2" type="extrapoint">
          <summary><![CDATA[8-R.Succop extra point is good.]]></summary>
          <links>
            <link href="/2014/REG/12/TEN/PHI/plays/d8475846-d4e4-48d6-b6b9-70977db7f7a6.xml" rel="summary" type="application/xml"/>
          </links>
        </score>
      </drive>
      <drive clock="08:22" quarter="2" sequence="7" team="PHI">
        <score clock="04:38" points="6" quarter="2" type="touchdown">
          <summary><![CDATA[25-L.McCoy runs 2 yards for a touchdown.]]></summary>
          <links>
            <link href="/2014/REG/12/TEN/PHI/plays/907e77f6-a56e-40f1-b85f-8c65fe5cffc4.xml" rel="summary" type="application/xml"/>
          </links>
        </score>
        <score clock="04:35" points="1" quarter="2" type="extrapoint">
          <summary><![CDATA[1-C.Parkey extra point is good.]]></summary>
          <links>
            <link href="/2014/REG/12/TEN/PHI/plays/d0cac50c-cde6-4320-9a97-cf6b40b92668.xml" rel="summary" type="application/xml"/>
          </links>
        </score>
      </drive>
      <drive clock="04:35" quarter="2" sequence="8" team="TEN">
        <score clock=":54" points="3" quarter="2" type="fieldgoal">
          <summary><![CDATA[8-R.Succop 20 yards Field Goal is Good.]]></summary>
          <links>
            <link href="/2014/REG/12/TEN/PHI/plays/de3f70c5-a466-42ca-a5c8-48b91cae505c.xml" rel="summary" type="application/xml"/>
          </links>
        </score>
      </drive>
      <drive clock="12:32" quarter="3" sequence="9" team="PHI">
        <score clock="11:33" points="6" quarter="3" type="touchdown">
          <summary><![CDATA[3-M.Sanchez complete to 85-J.Casey. 85-J.Casey runs 14 yards for a touchdown.]]></summary>
          <links>
            <link href="/2014/REG/12/TEN/PHI/plays/3bc52eb0-08d0-4506-ad67-458e567c4698.xml" rel="summary" type="application/xml"/>
          </links>
        </score>
        <score clock="11:27" points="1" quarter="3" type="extrapoint">
          <summary><![CDATA[1-C.Parkey extra point is good.]]></summary>
          <links>
            <link href="/2014/REG/12/TEN/PHI/plays/8c2ba1a9-b342-40f7-bb50-2100f27532f6.xml" rel="summary" type="application/xml"/>
          </links>
        </score>
      </drive>
      <drive clock="04:47" quarter="3" sequence="10" team="PHI">
        <score clock="14:17" points="3" quarter="4" type="fieldgoal">
          <summary><![CDATA[1-C.Parkey 35 yards Field Goal is Good.]]></summary>
          <links>
            <link href="/2014/REG/12/TEN/PHI/plays/55a9374c-e50c-43d3-b33c-cc3f5bfe24b6.xml" rel="summary" type="application/xml"/>
          </links>
        </score>
      </drive>
      <drive clock="12:26" quarter="4" sequence="11" team="PHI">
        <score clock="10:22" points="3" quarter="4" type="fieldgoal">
          <summary><![CDATA[1-C.Parkey 30 yards Field Goal is Good.]]></summary>
          <links>
            <link href="/2014/REG/12/TEN/PHI/plays/aa1fa30d-7bd8-470c-a259-abafc736c2f6.xml" rel="summary" type="application/xml"/>
          </links>
        </score>
      </drive>
      <drive clock="07:20" quarter="4" sequence="12" team="TEN">
        <score clock="05:48" points="6" quarter="4" type="touchdown">
          <summary><![CDATA[7-Z.Mettenberger complete to 22-D.McCluster. 22-D.McCluster runs 6 yards for a touchdown.]]></summary>
          <links>
            <link href="/2014/REG/12/TEN/PHI/plays/b395ac56-c106-47fa-b2ae-8b029337a986.xml" rel="summary" type="application/xml"/>
          </links>
        </score>
        <score clock="05:43" points="1" quarter="4" type="extrapoint">
          <summary><![CDATA[8-R.Succop extra point is good.]]></summary>
          <links>
            <link href="/2014/REG/12/TEN/PHI/plays/b840ec91-33aa-4f0b-a0c1-15ee4df31493.xml" rel="summary" type="application/xml"/>
          </links>
        </score>
      </drive>
      <drive clock="05:43" quarter="4" sequence="13" team="PHI">
        <score clock="02:31" points="3" quarter="4" type="fieldgoal">
          <summary><![CDATA[1-C.Parkey 50 yards Field Goal is Good.]]></summary>
          <links>
            <link href="/2014/REG/12/TEN/PHI/plays/058d9763-ad0c-4e01-a39e-7d98b424a7d4.xml" rel="summary" type="application/xml"/>
          </links>
        </score>
      </drive>
    </scoring_drives>
  </game>
  <game away="BAL" clock=":00" completed="2014-11-25T04:38:25+00:00" home="NO" id="e14c8385-836c-4852-ab37-cb03e4223a4b" quarter="4" scheduled="2014-11-25T01:30:00+00:00" status="closed">
    <team id="NO" market="New Orleans" name="Saints" remaining_challenges="1" remaining_timeouts="2">
      <scoring points="27">
        <quarter number="1" points="7"/>
        <quarter number="2" points="10"/>
        <quarter number="3" points="0"/>
        <quarter number="4" points="10"/>
      </scoring>
    </team>
    <team id="BAL" market="Baltimore" name="Ravens" remaining_challenges="1" remaining_timeouts="2">
      <scoring points="34">
        <quarter number="1" points="7"/>
        <quarter number="2" points="7"/>
        <quarter number="3" points="10"/>
        <quarter number="4" points="10"/>
      </scoring>
    </team>
    <scoring_drives>
      <drive clock="08:18" quarter="1" sequence="1" team="BAL">
        <score clock="08:18" points="6" quarter="1" type="touchdown">
          <summary><![CDATA[5-J.Flacco complete to 89-S.Smith. 89-S.Smith runs 15 yards for a touchdown.]]></summary>
          <links>
            <link href="/2014/REG/12/BAL/NO/plays/50902391-51c2-4365-8889-e292f9cc2216.xml" rel="summary" type="application/xml"/>
          </links>
        </score>
        <score clock="08:13" points="1" quarter="1" type="extrapoint">
          <summary><![CDATA[9-J.Tucker extra point is good.]]></summary>
          <links>
            <link href="/2014/REG/12/BAL/NO/plays/5f73f424-9e04-485a-b95c-004f962c0aaf.xml" rel="summary" type="application/xml"/>
          </links>
        </score>
      </drive>
      <drive clock="06:04" quarter="1" sequence="2" team="NO">
        <score clock="03:26" points="6" quarter="1" type="touchdown">
          <summary><![CDATA[9-D.Brees complete to 80-J.Graham. 80-J.Graham runs 10 yards for a touchdown.]]></summary>
          <links>
            <link href="/2014/REG/12/BAL/NO/plays/0e955af5-94e0-4c4a-9383-4d1e0875bde7.xml" rel="summary" type="application/xml"/>
          </links>
        </score>
        <score clock="03:20" points="1" quarter="1" type="extrapoint">
          <summary><![CDATA[3-S.Graham extra point is good.]]></summary>
          <links>
            <link href="/2014/REG/12/BAL/NO/plays/58a914c3-d0ce-439f-af5f-b7ad65b76828.xml" rel="summary" type="application/xml"/>
          </links>
        </score>
      </drive>
      <drive clock="11:13" quarter="2" sequence="3" team="BAL">
        <score clock="09:14" points="6" quarter="2" type="touchdown">
          <summary><![CDATA[29-J.Forsett runs 13 yards for a touchdown.]]></summary>
          <links>
            <link href="/2014/REG/12/BAL/NO/plays/33382daa-e0a8-40a9-88ef-7fc94efddd9a.xml" rel="summary" type="application/xml"/>
          </links>
        </score>
        <score clock="09:08" points="1" quarter="2" type="extrapoint">
          <summary><![CDATA[9-J.Tucker extra point is good.]]></summary>
          <links>
            <link href="/2014/REG/12/BAL/NO/plays/bc6fbff1-978d-423c-98e8-8cc3a7817d60.xml" rel="summary" type="application/xml"/>
          </links>
        </score>
      </drive>
      <drive clock="09:08" quarter="2" sequence="4" team="NO">
        <score clock="04:03" points="3" quarter="2" type="fieldgoal">
          <summary><![CDATA[3-S.Graham 20 yards Field Goal is Good.]]></summary>
          <links>
            <link href="/2014/REG/12/BAL/NO/plays/eb8cb33c-2f15-4072-9a08-f21d97c695f9.xml" rel="summary" type="application/xml"/>
          </links>
        </score>
      </drive>
      <drive clock="01:51" quarter="2" sequence="5" team="NO">
        <score clock=":24" points="6" quarter="2" type="touchdown">
          <summary><![CDATA[9-D.Brees complete to 12-M.Colston. 12-M.Colston runs 26 yards for a touchdown.]]></summary>
          <links>
            <link href="/2014/REG/12/BAL/NO/plays/9c26a44b-40f3-4133-8622-0e7e5f54525a.xml" rel="summary" type="application/xml"/>
          </links>
        </score>
        <score clock=":17" points="1" quarter="2" type="extrapoint">
          <summary><![CDATA[3-S.Graham extra point is good.]]></summary>
          <links>
            <link href="/2014/REG/12/BAL/NO/plays/2af0c114-0091-41b6-aa9a-ac741dacf25b.xml" rel="summary" type="application/xml"/>
          </links>
        </score>
      </drive>
      <drive clock="15:00" quarter="3" sequence="6" team="BAL">
        <score clock="08:36" points="3" quarter="3" type="fieldgoal">
          <summary><![CDATA[9-J.Tucker 31 yards Field Goal is Good.]]></summary>
          <links>
            <link href="/2014/REG/12/BAL/NO/plays/2a36471f-2125-485d-af61-613e17daef40.xml" rel="summary" type="application/xml"/>
          </links>
        </score>
      </drive>
      <drive clock="08:30" quarter="3" sequence="7" team="NO">
        <score clock="05:10" points="6" quarter="3" type="touchdown">
          <summary><![CDATA[9-D.Brees incomplete. Intended for 80-J.Graham, INTERCEPTED by 33-W.Hill at NO 44. 33-W.Hill runs 44 yards for a touchdown.]]></summary>
          <links>
            <link href="/2014/REG/12/BAL/NO/plays/4a4a375e-264d-4388-adc1-5ef419cc76d5.xml" rel="summary" type="application/xml"/>
          </links>
        </score>
      </drive>
      <drive clock="04:59" quarter="3" sequence="8" team="BAL">
        <score clock="04:59" points="1" quarter="3" type="extrapoint">
          <summary><![CDATA[9-J.Tucker extra point is good.]]></summary>
          <links>
            <link href="/2014/REG/12/BAL/NO/plays/9439630f-bfb0-4961-8d8a-8644597e9f6a.xml" rel="summary" type="application/xml"/>
          </links>
        </score>
      </drive>
      <drive clock="02:25" quarter="3" sequence="9" team="BAL">
        <score clock="11:04" points="3" quarter="4" type="fieldgoal">
          <summary><![CDATA[9-J.Tucker 55 yards Field Goal is Good.]]></summary>
          <links>
            <link href="/2014/REG/12/BAL/NO/plays/62d600a0-9160-4cf7-82d3-1bb516f7f067.xml" rel="summary" type="application/xml"/>
          </links>
        </score>
      </drive>
      <drive clock="10:59" quarter="4" sequence="10" team="NO">
        <score clock="06:38" points="3" quarter="4" type="fieldgoal">
          <summary><![CDATA[3-S.Graham 34 yards Field Goal is Good.]]></summary>
          <links>
            <link href="/2014/REG/12/BAL/NO/plays/b9ce99f9-74fa-466b-97eb-0dbfe4c534c5.xml" rel="summary" type="application/xml"/>
          </links>
        </score>
      </drive>
      <drive clock="06:33" quarter="4" sequence="11" team="BAL">
        <score clock="02:59" points="6" quarter="4" type="touchdown">
          <summary><![CDATA[29-J.Forsett runs 20 yards for a touchdown.]]></summary>
          <links>
            <link href="/2014/REG/12/BAL/NO/plays/76641942-0305-46d0-8b26-6afceef376e0.xml" rel="summary" type="application/xml"/>
          </links>
        </score>
        <score clock="02:53" points="1" quarter="4" type="extrapoint">
          <summary><![CDATA[9-J.Tucker extra point is good.]]></summary>
          <links>
            <link href="/2014/REG/12/BAL/NO/plays/1af888c3-dcf2-4bdf-8073-e2145cbc195a.xml" rel="summary" type="application/xml"/>
          </links>
        </score>
      </drive>
      <drive clock="02:53" quarter="4" sequence="12" team="NO">
        <score clock=":44" points="6" quarter="4" type="touchdown">
          <summary><![CDATA[9-D.Brees complete to 80-J.Graham. 80-J.Graham runs 2 yards for a touchdown.]]></summary>
          <links>
            <link href="/2014/REG/12/BAL/NO/plays/91775eae-9022-4ddb-a8da-6400dbf07bea.xml" rel="summary" type="application/xml"/>
          </links>
        </score>
        <score clock=":40" points="1" quarter="4" type="extrapoint">
          <summary><![CDATA[3-S.Graham extra point is good.]]></summary>
          <links>
            <link href="/2014/REG/12/BAL/NO/plays/fb30ed4b-567c-4569-be9e-cb5f055ea7d4.xml" rel="summary" type="application/xml"/>
          </links>
        </score>
      </drive>
    </scoring_drives>
  </game>
  <game away="KC" clock=":00" completed="2014-11-21T04:38:22+00:00" home="OAK" id="d955abb4-a84a-4815-9d28-2727d2a5b624" quarter="4" scheduled="2014-11-21T01:25:00+00:00" status="closed">
    <team id="OAK" market="Oakland" name="Raiders" remaining_challenges="2" remaining_timeouts="2">
      <scoring points="24">
        <quarter number="1" points="7"/>
        <quarter number="2" points="7"/>
        <quarter number="3" points="3"/>
        <quarter number="4" points="7"/>
      </scoring>
    </team>
    <team id="KC" market="Kansas City" name="Chiefs" remaining_challenges="2" remaining_timeouts="2">
      <scoring points="20">
        <quarter number="1" points="0"/>
        <quarter number="2" points="3"/>
        <quarter number="3" points="7"/>
        <quarter number="4" points="10"/>
      </scoring>
    </team>
    <scoring_drives>
      <drive clock="10:02" quarter="1" sequence="1" team="OAK">
        <score clock="06:39" points="6" quarter="1" type="touchdown">
          <summary><![CDATA[28-L.Murray runs 11 yards for a touchdown.]]></summary>
          <links>
            <link href="/2014/REG/12/KC/OAK/plays/37f0710d-35c0-4038-9ce4-b6622ab9dbbb.xml" rel="summary" type="application/xml"/>
          </links>
        </score>
        <score clock="06:33" points="1" quarter="1" type="extrapoint">
          <summary><![CDATA[11-S.Janikowski extra point is good.]]></summary>
          <links>
            <link href="/2014/REG/12/KC/OAK/plays/f86b8941-a2ab-4dcc-817d-4dbdaeab398c.xml" rel="summary" type="application/xml"/>
          </links>
        </score>
      </drive>
      <drive clock="12:40" quarter="2" sequence="2" team="OAK">
        <score clock="12:40" points="6" quarter="2" type="touchdown">
          <summary><![CDATA[28-L.Murray runs 90 yards for a touchdown.]]></summary>
          <links>
            <link href="/2014/REG/12/KC/OAK/plays/3fb7e4d0-5dc5-4b15-bafb-a30c3c54bc3b.xml" rel="summary" type="application/xml"/>
          </links>
        </score>
        <score clock="12:28" points="1" quarter="2" type="extrapoint">
          <summary><![CDATA[11-S.Janikowski extra point is good.]]></summary>
          <links>
            <link href="/2014/REG/12/KC/OAK/plays/1d8fb6de-5d78-407e-aa91-7f3933fe7b82.xml" rel="summary" type="application/xml"/>
          </links>
        </score>
      </drive>
      <drive clock="12:28" quarter="2" sequence="3" team="KC">
        <score clock="07:23" points="3" quarter="2" type="fieldgoal">
          <summary><![CDATA[5-C.Santos 24 yards Field Goal is Good.]]></summary>
          <links>
            <link href="/2014/REG/12/KC/OAK/plays/ad65c91c-6e9e-4099-b129-dc142f752a38.xml" rel="summary" type="application/xml"/>
          </links>
        </score>
      </drive>
      <drive clock="09:44" quarter="3" sequence="4" team="OAK">
        <score clock="05:10" points="3" quarter="3" type="fieldgoal">
          <summary><![CDATA[11-S.Janikowski 40 yards Field Goal is Good.]]></summary>
          <links>
            <link href="/2014/REG/12/KC/OAK/plays/9079a77d-6aa8-40d5-aaf8-525ad217007e.xml" rel="summary" type="application/xml"/>
          </links>
        </score>
      </drive>
      <drive clock="05:05" quarter="3" sequence="5" team="KC">
        <score clock="01:58" points="6" quarter="3" type="touchdown">
          <summary><![CDATA[11-A.Smith complete to 80-A.Fasano. 80-A.Fasano runs 19 yards for a touchdown.]]></summary>
          <links>
            <link href="/2014/REG/12/KC/OAK/plays/7d84d73c-8495-4bc3-b4c9-c5c32beaf2df.xml" rel="summary" type="application/xml"/>
          </links>
        </score>
        <score clock="01:52" points="1" quarter="3" type="extrapoint">
          <summary><![CDATA[5-C.Santos extra point is good.]]></summary>
          <links>
            <link href="/2014/REG/12/KC/OAK/plays/6c282df8-c2b8-4866-b139-8929239530e5.xml" rel="summary" type="application/xml"/>
          </links>
        </score>
      </drive>
      <drive clock="14:39" quarter="4" sequence="6" team="KC">
        <score clock="12:29" points="6" quarter="4" type="touchdown">
          <summary><![CDATA[11-A.Smith complete to 25-J.Charles. 25-J.Charles runs 30 yards for a touchdown.]]></summary>
          <links>
            <link href="/2014/REG/12/KC/OAK/plays/60634005-5008-4a20-a855-eb1189c9c650.xml" rel="summary" type="application/xml"/>
          </links>
        </score>
        <score clock="12:20" points="1" quarter="4" type="extrapoint">
          <summary><![CDATA[5-C.Santos extra point is good.]]></summary>
          <links>
            <link href="/2014/REG/12/KC/OAK/plays/c13ca5c5-f0d4-432e-aed8-c3373f7c71a6.xml" rel="summary" type="application/xml"/>
          </links>
        </score>
      </drive>
      <drive clock="11:13" quarter="4" sequence="7" team="KC">
        <score clock="09:07" points="3" quarter="4" type="fieldgoal">
          <summary><![CDATA[5-C.Santos 25 yards Field Goal is Good.]]></summary>
          <links>
            <link href="/2014/REG/12/KC/OAK/plays/cbd8f979-9b9c-4437-a5df-7f94391ddc6d.xml" rel="summary" type="application/xml"/>
          </links>
        </score>
      </drive>
      <drive clock="09:03" quarter="4" sequence="8" team="OAK">
        <score clock="01:46" points="6" quarter="4" type="touchdown">
          <summary><![CDATA[4-D.Carr complete to 89-J.Jones. 89-J.Jones runs 9 yards for a touchdown.]]></summary>
          <links>
            <link href="/2014/REG/12/KC/OAK/plays/151034e4-1f51-4908-b883-014212534239.xml" rel="summary" type="application/xml"/>
          </links>
        </score>
        <score clock="01:42" points="1" quarter="4" type="extrapoint">
          <summary><![CDATA[11-S.Janikowski extra point is good.]]></summary>
          <links>
            <link href="/2014/REG/12/KC/OAK/plays/22827427-e1ca-4ede-9d34-283cec199af1.xml" rel="summary" type="application/xml"/>
          </links>
        </score>
      </drive>
    </scoring_drives>
  </game>
  <game away="DAL" clock=":00" completed="2014-11-24T04:48:30+00:00" home="NYG" id="a5693554-f7c8-484f-92e6-9e05c32f6191" quarter="4" scheduled="2014-11-24T01:30:00+00:00" status="closed">
    <team id="NYG" market="New York" name="Giants" remaining_challenges="2" remaining_timeouts="2">
      <scoring points="28">
        <quarter number="1" points="7"/>
        <quarter number="2" points="14"/>
        <quarter number="3" points="0"/>
        <quarter number="4" points="7"/>
      </scoring>
    </team>
    <team id="DAL" market="Dallas" name="Cowboys" remaining_challenges="1" remaining_timeouts="2">
      <scoring points="31">
        <quarter number="1" points="3"/>
        <quarter number="2" points="7"/>
        <quarter number="3" points="14"/>
        <quarter number="4" points="7"/>
      </scoring>
    </team>
    <scoring_drives>
      <drive clock="14:08" quarter="1" sequence="1" team="NYG">
        <score clock="07:06" points="6" quarter="1" type="touchdown">
          <summary><![CDATA[10-E.Manning complete to 13-O.Beckham Jr. 13-O.Beckham Jr. runs 3 yards for a touchdown.]]></summary>
          <links>
            <link href="/2014/REG/12/DAL/NYG/plays/138c29ee-2b97-414f-b47c-a8e42bbc5368.xml" rel="summary" type="application/xml"/>
          </links>
        </score>
        <score clock="07:01" points="1" quarter="1" type="extrapoint">
          <summary><![CDATA[3-J.Brown extra point is good.]]></summary>
          <links>
            <link href="/2014/REG/12/DAL/NYG/plays/ce834055-a2ff-4d53-9fbe-d3a4901e1b0a.xml" rel="summary" type="application/xml"/>
          </links>
        </score>
      </drive>
      <drive clock="07:01" quarter="1" sequence="2" team="DAL">
        <score clock="02:50" points="3" quarter="1" type="fieldgoal">
          <summary><![CDATA[5-D.Bailey 38 yards Field Goal is Good.]]></summary>
          <links>
            <link href="/2014/REG/12/DAL/NYG/plays/fe84e58d-cb9e-44f5-ba7d-ad17db064b5d.xml" rel="summary" type="application/xml"/>
          </links>
        </score>
      </drive>
      <drive clock="02:45" quarter="1" sequence="3" team="NYG">
        <score clock="15:00" points="6" quarter="2" type="touchdown">
          <summary><![CDATA[10-E.Manning complete to 13-O.Beckham Jr. 13-O.Beckham Jr. runs 43 yards for a touchdown. Penalty on DAL 39-B.Carr, Pass interference, declined.]]></summary>
          <links>
            <link href="/2014/REG/12/DAL/NYG/plays/f2283d04-e78c-40be-b4d0-b5504f9a0ae9.xml" rel="summary" type="application/xml"/>
          </links>
        </score>
        <score clock="14:52" points="1" quarter="2" type="extrapoint">
          <summary><![CDATA[3-J.Brown extra point is good.]]></summary>
          <links>
            <link href="/2014/REG/12/DAL/NYG/plays/a8b752e1-1ea6-4013-be9a-ffde7e87d30e.xml" rel="summary" type="application/xml"/>
          </links>
        </score>
      </drive>
      <drive clock="14:52" quarter="2" sequence="4" team="DAL">
        <score clock="09:19" points="6" quarter="2" type="touchdown">
          <summary><![CDATA[9-T.Romo complete to 82-J.Witten. 82-J.Witten runs 4 yards for a touchdown.]]></summary>
          <links>
            <link href="/2014/REG/12/DAL/NYG/plays/727882c0-ba4d-4996-bd1e-8946d42ea19d.xml" rel="summary" type="application/xml"/>
          </links>
        </score>
        <score clock="09:15" points="1" quarter="2" type="extrapoint">
          <summary><![CDATA[5-D.Bailey extra point is good.]]></summary>
          <links>
            <link href="/2014/REG/12/DAL/NYG/plays/8f3851ef-c3c8-4759-bbb2-b4f02fd31f5f.xml" rel="summary" type="application/xml"/>
          </links>
        </score>
      </drive>
      <drive clock="09:15" quarter="2" sequence="5" team="NYG">
        <score clock="03:22" points="6" quarter="2" type="touchdown">
          <summary><![CDATA[44-A.Williams runs 3 yards for a touchdown.]]></summary>
          <links>
            <link href="/2014/REG/12/DAL/NYG/plays/7e51f4de-52d7-4f98-9a19-a3bee4e25ebc.xml" rel="summary" type="application/xml"/>
          </links>
        </score>
        <score clock="03:18" points="1" quarter="2" type="extrapoint">
          <summary><![CDATA[3-J.Brown extra point is good.]]></summary>
          <links>
            <link href="/2014/REG/12/DAL/NYG/plays/11815bbb-1d9a-4b1e-8fe9-99c1af0656e8.xml" rel="summary" type="application/xml"/>
          </links>
        </score>
      </drive>
      <drive clock="08:34" quarter="3" sequence="6" team="DAL">
        <score clock="06:45" points="6" quarter="3" type="touchdown">
          <summary><![CDATA[9-T.Romo complete to 11-C.Beasley. 11-C.Beasley runs 45 yards for a touchdown.]]></summary>
          <links>
            <link href="/2014/REG/12/DAL/NYG/plays/5961456c-8118-4254-b5a3-9a4b1ecf0685.xml" rel="summary" type="application/xml"/>
          </links>
        </score>
        <score clock="06:35" points="1" quarter="3" type="extrapoint">
          <summary><![CDATA[5-D.Bailey extra point is good.]]></summary>
          <links>
            <link href="/2014/REG/12/DAL/NYG/plays/2e818563-dfc4-4bdd-a02f-b218537ce98e.xml" rel="summary" type="application/xml"/>
          </links>
        </score>
      </drive>
      <drive clock="03:03" quarter="3" sequence="7" team="DAL">
        <score clock="01:18" points="6" quarter="3" type="touchdown">
          <summary><![CDATA[9-T.Romo complete to 88-D.Bryant. 88-D.Bryant runs 31 yards for a touchdown.]]></summary>
          <links>
            <link href="/2014/REG/12/DAL/NYG/plays/2af3ac33-4703-406f-9fdf-790f22fe0589.xml" rel="summary" type="application/xml"/>
          </links>
        </score>
        <score clock="01:08" points="1" quarter="3" type="extrapoint">
          <summary><![CDATA[5-D.Bailey extra point is good.]]></summary>
          <links>
            <link href="/2014/REG/12/DAL/NYG/plays/befdaee3-3bdc-4d21-bcb5-6d1ee911ebbb.xml" rel="summary" type="application/xml"/>
          </links>
        </score>
      </drive>
      <drive clock="09:12" quarter="4" sequence="8" team="NYG">
        <score clock="03:05" points="6" quarter="4" type="touchdown">
          <summary><![CDATA[10-E.Manning complete to 81-A.Robinson. 81-A.Robinson runs 1 yard for a touchdown.]]></summary>
          <links>
            <link href="/2014/REG/12/DAL/NYG/plays/c8c7b6af-2bf4-4ccc-b747-abaa4b7e9cc9.xml" rel="summary" type="application/xml"/>
          </links>
        </score>
        <score clock="03:00" points="1" quarter="4" type="extrapoint">
          <summary><![CDATA[3-J.Brown extra point is good.]]></summary>
          <links>
            <link href="/2014/REG/12/DAL/NYG/plays/f52b9172-db27-417b-9754-d112f8484e89.xml" rel="summary" type="application/xml"/>
          </links>
        </score>
      </drive>
      <drive clock="03:00" quarter="4" sequence="9" team="DAL">
        <score clock="01:11" points="6" quarter="4" type="touchdown">
          <summary><![CDATA[9-T.Romo complete to 88-D.Bryant. 88-D.Bryant runs 13 yards for a touchdown.]]></summary>
          <links>
            <link href="/2014/REG/12/DAL/NYG/plays/fed30ca7-0b46-4161-824c-9f9295bd0da0.xml" rel="summary" type="application/xml"/>
          </links>
        </score>
        <score clock="01:01" points="1" quarter="4" type="extrapoint">
          <summary><![CDATA[5-D.Bailey extra point is good.]]></summary>
          <links>
            <link href="/2014/REG/12/DAL/NYG/plays/a1402ac9-a447-4eb1-9005-4a8384112206.xml" rel="summary" type="application/xml"/>
          </links>
        </score>
      </drive>
    </scoring_drives>
  </game>
  <game away="GB" clock=":00" completed="2014-11-23T21:00:31+00:00" home="MIN" id="e8a2a5e6-dcc4-4357-9b8e-b6cbcb34c03c" quarter="4" scheduled="2014-11-23T18:00:00+00:00" status="closed">
    <team id="MIN" market="Minnesota" name="Vikings" remaining_challenges="2" remaining_timeouts="2">
      <scoring points="21">
        <quarter number="1" points="0"/>
        <quarter number="2" points="10"/>
        <quarter number="3" points="3"/>
        <quarter number="4" points="8"/>
      </scoring>
    </team>
    <team id="GB" market="Green Bay" name="Packers" remaining_challenges="1" remaining_timeouts="2">
      <scoring points="24">
        <quarter number="1" points="7"/>
        <quarter number="2" points="7"/>
        <quarter number="3" points="3"/>
        <quarter number="4" points="7"/>
      </scoring>
    </team>
    <scoring_drives>
      <drive clock="04:44" quarter="1" sequence="1" team="GB">
        <score clock="01:37" points="6" quarter="1" type="touchdown">
          <summary><![CDATA[27-E.Lacy runs 1 yard for a touchdown.]]></summary>
          <links>
            <link href="/2014/REG/12/GB/MIN/plays/795be528-5f45-47c6-9cd8-19912c74e6ca.xml" rel="summary" type="application/xml"/>
          </links>
        </score>
        <score clock="01:34" points="1" quarter="1" type="extrapoint">
          <summary><![CDATA[2-M.Crosby extra point is good.]]></summary>
          <links>
            <link href="/2014/REG/12/GB/MIN/plays/2ca7a295-3194-4522-bcca-2e357419f47a.xml" rel="summary" type="application/xml"/>
          </links>
        </score>
      </drive>
      <drive clock="01:34" quarter="1" sequence="2" team="MIN">
        <score clock="11:12" points="6" quarter="2" type="touchdown">
          <summary><![CDATA[5-T.Bridgewater complete to 12-C.Johnson. 12-C.Johnson runs 22 yards for a touchdown.]]></summary>
          <links>
            <link href="/2014/REG/12/GB/MIN/plays/53a660f1-0b1d-4ca6-b83a-280f850eb320.xml" rel="summary" type="application/xml"/>
          </links>
        </score>
        <score clock="11:06" points="1" quarter="2" type="extrapoint">
          <summary><![CDATA[3-B.Walsh extra point is good.]]></summary>
          <links>
            <link href="/2014/REG/12/GB/MIN/plays/a7d61149-8396-4133-a093-642aff2dd74a.xml" rel="summary" type="application/xml"/>
          </links>
        </score>
      </drive>
      <drive clock="07:22" quarter="2" sequence="3" team="GB">
        <score clock="05:30" points="6" quarter="2" type="touchdown">
          <summary><![CDATA[12-A.Rodgers complete to 89-R.Rodgers. 89-R.Rodgers runs 1 yard for a touchdown. Penalty on MIN 54-J.Brinkley, Holding, declined.]]></summary>
          <links>
            <link href="/2014/REG/12/GB/MIN/plays/d244acc5-3ca6-47c1-877d-4a7549afc570.xml" rel="summary" type="application/xml"/>
          </links>
        </score>
        <score clock="05:23" points="1" quarter="2" type="extrapoint">
          <summary><![CDATA[2-M.Crosby extra point is good.]]></summary>
          <links>
            <link href="/2014/REG/12/GB/MIN/plays/7dca4854-f270-4ad6-90a0-c0929af127c0.xml" rel="summary" type="application/xml"/>
          </links>
        </score>
      </drive>
      <drive clock="05:23" quarter="2" sequence="4" team="MIN">
        <score clock=":21" points="3" quarter="2" type="fieldgoal">
          <summary><![CDATA[3-B.Walsh 39 yards Field Goal is Good.]]></summary>
          <links>
            <link href="/2014/REG/12/GB/MIN/plays/d3fdab90-e770-4c52-bf13-9f35f91e8b7b.xml" rel="summary" type="application/xml"/>
          </links>
        </score>
      </drive>
      <drive clock="08:35" quarter="3" sequence="5" team="MIN">
        <score clock="06:47" points="3" quarter="3" type="fieldgoal">
          <summary><![CDATA[3-B.Walsh 51 yards Field Goal is Good.]]></summary>
          <links>
            <link href="/2014/REG/12/GB/MIN/plays/beafeeb6-a90d-46b3-9dab-9429917b703e.xml" rel="summary" type="application/xml"/>
          </links>
        </score>
      </drive>
      <drive clock="06:42" quarter="3" sequence="6" team="GB">
        <score clock="02:54" points="3" quarter="3" type="fieldgoal">
          <summary><![CDATA[2-M.Crosby 48 yards Field Goal is Good.]]></summary>
          <links>
            <link href="/2014/REG/12/GB/MIN/plays/b641fcb5-38f2-4204-aa25-46fe6c958095.xml" rel="summary" type="application/xml"/>
          </links>
        </score>
      </drive>
      <drive clock="14:52" quarter="4" sequence="7" team="GB">
        <score clock="08:41" points="6" quarter="4" type="touchdown">
          <summary><![CDATA[12-A.Rodgers complete to 27-E.Lacy. 27-E.Lacy runs 10 yards for a touchdown.]]></summary>
          <links>
            <link href="/2014/REG/12/GB/MIN/plays/145fa267-b663-4499-b4b0-4b9babcd8bbc.xml" rel="summary" type="application/xml"/>
          </links>
        </score>
        <score clock="08:34" points="1" quarter="4" type="extrapoint">
          <summary><![CDATA[2-M.Crosby extra point is good.]]></summary>
          <links>
            <link href="/2014/REG/12/GB/MIN/plays/9bda161f-1f64-4c4f-885b-cda721664835.xml" rel="summary" type="application/xml"/>
          </links>
        </score>
      </drive>
      <drive clock="08:34" quarter="4" sequence="8" team="MIN">
        <score clock="03:28" points="6" quarter="4" type="touchdown">
          <summary><![CDATA[5-T.Bridgewater complete to 15-G.Jennings. 15-G.Jennings runs 5 yards for a touchdown.]]></summary>
          <links>
            <link href="/2014/REG/12/GB/MIN/plays/9bb0ab17-c92f-4a84-a3b1-3c129395d8cd.xml" rel="summary" type="application/xml"/>
          </links>
        </score>
        <score clock="03:23" points="2" quarter="4" type="conversion">
          <summary><![CDATA[5-T.Bridgewater complete to 12-C.Johnson. 12-C.Johnson to GB End Zone for 2 yards. Conversion is good.]]></summary>
          <links>
            <link href="/2014/REG/12/GB/MIN/plays/80f41c40-d9dd-48e1-aa6e-9305c208022e.xml" rel="summary" type="application/xml"/>
          </links>
        </score>
      </drive>
    </scoring_drives>
  </game>
  <game away="CIN" clock=":00" completed="2014-11-23T21:04:40+00:00" home="HOU" id="de8f27ac-1c44-4483-98d0-668771c72c04" quarter="4" scheduled="2014-11-23T18:00:00+00:00" status="closed">
    <team id="HOU" market="Houston" name="Texans" remaining_challenges="2" remaining_timeouts="2">
      <scoring points="13">
        <quarter number="1" points="0"/>
        <quarter number="2" points="3"/>
        <quarter number="3" points="10"/>
        <quarter number="4" points="0"/>
      </scoring>
    </team>
    <team id="CIN" market="Cincinnati" name="Bengals" remaining_challenges="1" remaining_timeouts="2">
      <scoring points="22">
        <quarter number="1" points="7"/>
        <quarter number="2" points="2"/>
        <quarter number="3" points="7"/>
        <quarter number="4" points="6"/>
      </scoring>
    </team>
    <scoring_drives>
      <drive clock="07:38" quarter="1" sequence="1" team="CIN">
        <score clock="01:25" points="6" quarter="1" type="touchdown">
          <summary><![CDATA[14-A.Dalton complete to 12-M.Sanu. 12-M.Sanu runs 6 yards for a touchdown.]]></summary>
          <links>
            <link href="/2014/REG/12/CIN/HOU/plays/90992d8d-8ae5-4bb5-bb7c-743a8abc2aeb.xml" rel="summary" type="application/xml"/>
          </links>
        </score>
        <score clock="01:19" points="1" quarter="1" type="extrapoint">
          <summary><![CDATA[2-M.Nugent extra point is good.]]></summary>
          <links>
            <link href="/2014/REG/12/CIN/HOU/plays/edc74ae3-e227-4f6d-90c1-ef5f76109d10.xml" rel="summary" type="application/xml"/>
          </links>
        </score>
      </drive>
      <drive clock="09:02" quarter="2" sequence="2" team="HOU">
        <score clock="09:02" points="2" quarter="2" type="safety">
          <summary><![CDATA[28-A.Blue to HOU End Zone for -1 yard (97-G.Atkins). to HOU End Zone for -1 yard, safety.]]></summary>
          <links>
            <link href="/2014/REG/12/CIN/HOU/plays/582f0c2e-4c44-4e1f-bbb9-b4c5c4774423.xml" rel="summary" type="application/xml"/>
          </links>
        </score>
      </drive>
      <drive clock="06:49" quarter="2" sequence="3" team="HOU">
        <score clock="01:45" points="3" quarter="2" type="fieldgoal">
          <summary><![CDATA[4-R.Bullock 36 yards Field Goal is Good.]]></summary>
          <links>
            <link href="/2014/REG/12/CIN/HOU/plays/891cd022-504a-4809-a58d-957cab363242.xml" rel="summary" type="application/xml"/>
          </links>
        </score>
      </drive>
      <drive clock="14:46" quarter="3" sequence="4" team="CIN">
        <score clock="11:52" points="6" quarter="3" type="touchdown">
          <summary><![CDATA[32-J.Hill runs 2 yards for a touchdown.]]></summary>
          <links>
            <link href="/2014/REG/12/CIN/HOU/plays/4146dd60-b8b6-4468-ae47-9a2397488c00.xml" rel="summary" type="application/xml"/>
          </links>
        </score>
        <score clock="11:48" points="1" quarter="3" type="extrapoint">
          <summary><![CDATA[2-M.Nugent extra point is good.]]></summary>
          <links>
            <link href="/2014/REG/12/CIN/HOU/plays/0d6efd7c-1b8d-40e7-9abb-131437dd0548.xml" rel="summary" type="application/xml"/>
          </links>
        </score>
      </drive>
      <drive clock="10:16" quarter="3" sequence="5" team="CIN">
        <score clock="07:30" points="6" quarter="3" type="touchdown">
          <summary><![CDATA[14-A.Dalton incomplete. Intended for 18-A.Green, INTERCEPTED by 24-J.Joseph at HOU 40. 24-J.Joseph runs 60 yards for a touchdown.]]></summary>
          <links>
            <link href="/2014/REG/12/CIN/HOU/plays/67e57b1e-acb6-4ed7-a638-cecdeb344b09.xml" rel="summary" type="application/xml"/>
          </links>
        </score>
      </drive>
      <drive clock="07:19" quarter="3" sequence="6" team="HOU">
        <score clock="07:19" points="1" quarter="3" type="extrapoint">
          <summary><![CDATA[4-R.Bullock extra point is good.]]></summary>
          <links>
            <link href="/2014/REG/12/CIN/HOU/plays/9f67a929-f49e-43dd-8ad2-3a507ec86772.xml" rel="summary" type="application/xml"/>
          </links>
        </score>
      </drive>
      <drive clock="06:14" quarter="3" sequence="7" team="HOU">
        <score clock="01:52" points="3" quarter="3" type="fieldgoal">
          <summary><![CDATA[4-R.Bullock 24 yards Field Goal is Good.]]></summary>
          <links>
            <link href="/2014/REG/12/CIN/HOU/plays/25f6c444-b137-4246-8653-8548f2d5f91d.xml" rel="summary" type="application/xml"/>
          </links>
        </score>
      </drive>
      <drive clock="01:48" quarter="3" sequence="8" team="CIN">
        <score clock="08:52" points="3" quarter="4" type="fieldgoal">
          <summary><![CDATA[2-M.Nugent 31 yards Field Goal is Good.]]></summary>
          <links>
            <link href="/2014/REG/12/CIN/HOU/plays/adfcd7c2-3dca-4277-bb2f-79aafc2065f7.xml" rel="summary" type="application/xml"/>
          </links>
        </score>
      </drive>
      <drive clock="04:56" quarter="4" sequence="9" team="CIN">
        <score clock="02:00" points="3" quarter="4" type="fieldgoal">
          <summary><![CDATA[2-M.Nugent 49 yards Field Goal is Good.]]></summary>
          <links>
            <link href="/2014/REG/12/CIN/HOU/plays/bb1e24e0-f7e4-4737-b5f5-f5d417778e7e.xml" rel="summary" type="application/xml"/>
          </links>
        </score>
      </drive>
    </scoring_drives>
  </game>
  <game away="DET" clock=":00" completed="2014-11-23T21:36:28+00:00" home="NE" id="1f2343b3-937b-474b-bfad-005035ba7c52" quarter="4" scheduled="2014-11-23T18:00:00+00:00" status="closed">
    <team id="NE" market="New England" name="Patriots" remaining_challenges="2" remaining_timeouts="1">
      <scoring points="34">
        <quarter number="1" points="7"/>
        <quarter number="2" points="17"/>
        <quarter number="3" points="3"/>
        <quarter number="4" points="7"/>
      </scoring>
    </team>
    <team id="DET" market="Detroit" name="Lions" remaining_challenges="1" remaining_timeouts="0">
      <scoring points="9">
        <quarter number="1" points="3"/>
        <quarter number="2" points="3"/>
        <quarter number="3" points="0"/>
        <quarter number="4" points="3"/>
      </scoring>
    </team>
    <scoring_drives>
      <drive clock="15:00" quarter="1" sequence="1" team="DET">
        <score clock="11:49" points="3" quarter="1" type="fieldgoal">
          <summary><![CDATA[5-M.Prater 48 yards Field Goal is Good.]]></summary>
          <links>
            <link href="/2014/REG/12/DET/NE/plays/4f0c7580-f23d-44b7-87bc-1c820a38a647.xml" rel="summary" type="application/xml"/>
          </links>
        </score>
      </drive>
      <drive clock="05:47" quarter="1" sequence="2" team="NE">
        <score clock="03:13" points="6" quarter="1" type="touchdown">
          <summary><![CDATA[12-T.Brady complete to 81-T.Wright. 81-T.Wright runs 4 yards for a touchdown.]]></summary>
          <links>
            <link href="/2014/REG/12/DET/NE/plays/9a817f6a-2614-4467-8c5f-6629b4ed6bce.xml" rel="summary" type="application/xml"/>
          </links>
        </score>
        <score clock="03:10" points="1" quarter="1" type="extrapoint">
          <summary><![CDATA[3-S.Gostkowski extra point is good.]]></summary>
          <links>
            <link href="/2014/REG/12/DET/NE/plays/e704c02d-6136-4233-a2be-c55b7a7c20d0.xml" rel="summary" type="application/xml"/>
          </links>
        </score>
      </drive>
      <drive clock="03:10" quarter="1" sequence="3" team="DET">
        <score clock="13:41" points="3" quarter="2" type="fieldgoal">
          <summary><![CDATA[5-M.Prater 20 yards Field Goal is Good.]]></summary>
          <links>
            <link href="/2014/REG/12/DET/NE/plays/8b74e489-2d90-49c6-b79b-bcd5a9dde280.xml" rel="summary" type="application/xml"/>
          </links>
        </score>
      </drive>
      <drive clock="13:37" quarter="2" sequence="4" team="NE">
        <score clock="12:46" points="6" quarter="2" type="touchdown">
          <summary><![CDATA[29-L.Blount runs 3 yards for a touchdown.]]></summary>
          <links>
            <link href="/2014/REG/12/DET/NE/plays/386b1d9d-7dbf-4111-b8fb-cc50b4219691.xml" rel="summary" type="application/xml"/>
          </links>
        </score>
        <score clock="12:43" points="1" quarter="2" type="extrapoint">
          <summary><![CDATA[3-S.Gostkowski extra point is good.]]></summary>
          <links>
            <link href="/2014/REG/12/DET/NE/plays/1b29869d-a61e-46af-b0fb-5948b8071985.xml" rel="summary" type="application/xml"/>
          </links>
        </score>
      </drive>
      <drive clock="07:45" quarter="2" sequence="5" team="NE">
        <score clock="02:47" points="6" quarter="2" type="touchdown">
          <summary><![CDATA[12-T.Brady complete to 81-T.Wright. 81-T.Wright runs 8 yards for a touchdown.]]></summary>
          <links>
            <link href="/2014/REG/12/DET/NE/plays/a2099db6-b5d1-4f90-bb7a-8504577b9991.xml" rel="summary" type="application/xml"/>
          </links>
        </score>
        <score clock="02:42" points="1" quarter="2" type="extrapoint">
          <summary><![CDATA[3-S.Gostkowski extra point is good.]]></summary>
          <links>
            <link href="/2014/REG/12/DET/NE/plays/5502c1ca-7985-4c28-8160-5878bc43e322.xml" rel="summary" type="application/xml"/>
          </links>
        </score>
      </drive>
      <drive clock=":35" quarter="2" sequence="6" team="NE">
        <score clock=":04" points="3" quarter="2" type="fieldgoal">
          <summary><![CDATA[3-S.Gostkowski 35 yards Field Goal is Good.]]></summary>
          <links>
            <link href="/2014/REG/12/DET/NE/plays/0b50b18f-959d-4768-8dc8-24001ef3a939.xml" rel="summary" type="application/xml"/>
          </links>
        </score>
      </drive>
      <drive clock="08:32" quarter="3" sequence="7" team="NE">
        <score clock="05:10" points="3" quarter="3" type="fieldgoal">
          <summary><![CDATA[3-S.Gostkowski 43 yards Field Goal is Good.]]></summary>
          <links>
            <link href="/2014/REG/12/DET/NE/plays/f9b00c88-8ca7-4965-bdd6-630c6a2dcbc9.xml" rel="summary" type="application/xml"/>
          </links>
        </score>
      </drive>
      <drive clock="02:54" quarter="3" sequence="8" team="DET">
        <score clock="14:53" points="3" quarter="4" type="fieldgoal">
          <summary><![CDATA[5-M.Prater 49 yards Field Goal is Good.]]></summary>
          <links>
            <link href="/2014/REG/12/DET/NE/plays/09f97f9f-8704-490f-b3c1-8d5061a3bdbd.xml" rel="summary" type="application/xml"/>
          </links>
        </score>
      </drive>
      <drive clock="06:23" quarter="4" sequence="9" team="NE">
        <score clock="01:57" points="6" quarter="4" type="touchdown">
          <summary><![CDATA[29-L.Blount runs 1 yard for a touchdown.]]></summary>
          <links>
            <link href="/2014/REG/12/DET/NE/plays/74c13f61-9257-4163-8338-17fc4be7c6c6.xml" rel="summary" type="application/xml"/>
          </links>
        </score>
        <score clock="01:53" points="1" quarter="4" type="extrapoint">
          <summary><![CDATA[3-S.Gostkowski extra point is good.]]></summary>
          <links>
            <link href="/2014/REG/12/DET/NE/plays/2cd8f0f4-5da1-4e5a-bc08-caf68efc9d21.xml" rel="summary" type="application/xml"/>
          </links>
        </score>
      </drive>
    </scoring_drives>
  </game>
  <game away="JAC" clock=":00" completed="2014-11-23T21:05:11+00:00" home="IND" id="8dd58e02-79f0-49e6-9ab3-7ba4cd933b1c" quarter="4" scheduled="2014-11-23T18:00:00+00:00" status="closed">
    <team id="IND" market="Indianapolis" name="Colts" remaining_challenges="2" remaining_timeouts="2">
      <scoring points="23">
        <quarter number="1" points="3"/>
        <quarter number="2" points="3"/>
        <quarter number="3" points="14"/>
        <quarter number="4" points="3"/>
      </scoring>
    </team>
    <team id="JAC" market="Jacksonville" name="Jaguars" remaining_challenges="0" remaining_timeouts="2">
      <scoring points="3">
        <quarter number="1" points="3"/>
        <quarter number="2" points="0"/>
        <quarter number="3" points="0"/>
        <quarter number="4" points="0"/>
      </scoring>
    </team>
    <scoring_drives>
      <drive clock="12:00" quarter="1" sequence="1" team="IND">
        <score clock="10:38" points="3" quarter="1" type="fieldgoal">
          <summary><![CDATA[4-A.Vinatieri 46 yards Field Goal is Good.]]></summary>
          <links>
            <link href="/2014/REG/12/JAC/IND/plays/9d312945-f80d-43a9-84f9-4dc303f68eb0.xml" rel="summary" type="application/xml"/>
          </links>
        </score>
      </drive>
      <drive clock="06:45" quarter="1" sequence="2" team="JAC">
        <score clock="04:22" points="3" quarter="1" type="fieldgoal">
          <summary><![CDATA[10-J.Scobee 28 yards Field Goal is Good.]]></summary>
          <links>
            <link href="/2014/REG/12/JAC/IND/plays/ca75de12-fb15-42d0-8a1c-dfe67783764a.xml" rel="summary" type="application/xml"/>
          </links>
        </score>
      </drive>
      <drive clock="02:31" quarter="2" sequence="3" team="IND">
        <score clock=":16" points="3" quarter="2" type="fieldgoal">
          <summary><![CDATA[4-A.Vinatieri 20 yards Field Goal is Good.]]></summary>
          <links>
            <link href="/2014/REG/12/JAC/IND/plays/6d071684-7183-4af1-9a0f-5c991c33411c.xml" rel="summary" type="application/xml"/>
          </links>
        </score>
      </drive>
      <drive clock="13:39" quarter="3" sequence="4" team="IND">
        <score clock="08:36" points="6" quarter="3" type="touchdown">
          <summary><![CDATA[34-T.Richardson runs 1 yard for a touchdown.]]></summary>
          <links>
            <link href="/2014/REG/12/JAC/IND/plays/9598cb49-f1a3-4654-8e5f-4fbae4119368.xml" rel="summary" type="application/xml"/>
          </links>
        </score>
        <score clock="08:31" points="1" quarter="3" type="extrapoint">
          <summary><![CDATA[4-A.Vinatieri extra point is good.]]></summary>
          <links>
            <link href="/2014/REG/12/JAC/IND/plays/dc659ffe-b65e-4617-839a-21eb6b4ce790.xml" rel="summary" type="application/xml"/>
          </links>
        </score>
      </drive>
      <drive clock="06:46" quarter="3" sequence="5" team="IND">
        <score clock="06:19" points="6" quarter="3" type="touchdown">
          <summary><![CDATA[12-A.Luck complete to 13-T.Y.Hilton. 13-T.Y.Hilton runs 73 yards for a touchdown.]]></summary>
          <links>
            <link href="/2014/REG/12/JAC/IND/plays/2f048930-660f-4070-807d-bed29a2d871b.xml" rel="summary" type="application/xml"/>
          </links>
        </score>
        <score clock="06:08" points="1" quarter="3" type="extrapoint">
          <summary><![CDATA[4-A.Vinatieri extra point is good.]]></summary>
          <links>
            <link href="/2014/REG/12/JAC/IND/plays/0cddbff1-8b88-4189-8b4d-9bd059ce0c3e.xml" rel="summary" type="application/xml"/>
          </links>
        </score>
      </drive>
      <drive clock="04:20" quarter="3" sequence="6" team="IND">
        <score clock="14:57" points="3" quarter="4" type="fieldgoal">
          <summary><![CDATA[4-A.Vinatieri 32 yards Field Goal is Good.]]></summary>
          <links>
            <link href="/2014/REG/12/JAC/IND/plays/90a3fdf7-b9c2-497b-be77-ad43491826b1.xml" rel="summary" type="application/xml"/>
          </links>
        </score>
      </drive>
    </scoring_drives>
  </game>
  <game away="ARI" clock=":00" completed="2014-11-23T23:51:59+00:00" home="SEA" id="7c6811c7-80d5-416d-91b7-15914e1cfe9b" quarter="4" scheduled="2014-11-23T21:05:00+00:00" status="closed">
    <team id="SEA" market="Seattle" name="Seahawks" remaining_challenges="1" remaining_timeouts="2">
      <scoring points="19">
        <quarter number="1" points="3"/>
        <quarter number="2" points="6"/>
        <quarter number="3" points="10"/>
        <quarter number="4" points="0"/>
      </scoring>
    </team>
    <team id="ARI" market="Arizona" name="Cardinals" remaining_challenges="2" remaining_timeouts="2">
      <scoring points="3">
        <quarter number="1" points="0"/>
        <quarter number="2" points="3"/>
        <quarter number="3" points="0"/>
        <quarter number="4" points="0"/>
      </scoring>
    </team>
    <scoring_drives>
      <drive clock="13:25" quarter="1" sequence="1" team="SEA">
        <score clock="08:49" points="3" quarter="1" type="fieldgoal">
          <summary><![CDATA[4-S.Hauschka 27 yards Field Goal is Good.]]></summary>
          <links>
            <link href="/2014/REG/12/ARI/SEA/plays/cf1161e7-1ccb-4413-9eff-e0b0e88a144b.xml" rel="summary" type="application/xml"/>
          </links>
        </score>
      </drive>
      <drive clock=":30" quarter="1" sequence="2" team="SEA">
        <score clock="12:56" points="3" quarter="2" type="fieldgoal">
          <summary><![CDATA[4-S.Hauschka 32 yards Field Goal is Good.]]></summary>
          <links>
            <link href="/2014/REG/12/ARI/SEA/plays/0ebd5651-c0b6-43e2-be4d-b6f39ddc8dc2.xml" rel="summary" type="application/xml"/>
          </links>
        </score>
      </drive>
      <drive clock="12:01" quarter="2" sequence="3" team="SEA">
        <score clock="10:15" points="3" quarter="2" type="fieldgoal">
          <summary><![CDATA[4-S.Hauschka 52 yards Field Goal is Good.]]></summary>
          <links>
            <link href="/2014/REG/12/ARI/SEA/plays/6c81cb08-2e11-4a93-9238-1e73cb5165da.xml" rel="summary" type="application/xml"/>
          </links>
        </score>
      </drive>
      <drive clock="05:28" quarter="2" sequence="4" team="ARI">
        <score clock=":16" points="3" quarter="2" type="fieldgoal">
          <summary><![CDATA[7-C.Catanzaro 23 yards Field Goal is Good.]]></summary>
          <links>
            <link href="/2014/REG/12/ARI/SEA/plays/1abf16bc-216b-41c4-8b87-f740b6f5aa7e.xml" rel="summary" type="application/xml"/>
          </links>
        </score>
      </drive>
      <drive clock="11:04" quarter="3" sequence="5" team="SEA">
        <score clock="08:39" points="3" quarter="3" type="fieldgoal">
          <summary><![CDATA[4-S.Hauschka 40 yards Field Goal is Good.]]></summary>
          <links>
            <link href="/2014/REG/12/ARI/SEA/plays/d497b7f6-9f57-44d6-af01-d438f34fa40e.xml" rel="summary" type="application/xml"/>
          </links>
        </score>
      </drive>
      <drive clock="06:33" quarter="3" sequence="6" team="SEA">
        <score clock="01:02" points="6" quarter="3" type="touchdown">
          <summary><![CDATA[3-R.Wilson complete to 84-C.Helfet. 84-C.Helfet runs 20 yards for a touchdown.]]></summary>
          <links>
            <link href="/2014/REG/12/ARI/SEA/plays/275d8006-01fa-405d-bbc7-f5ebe33b144c.xml" rel="summary" type="application/xml"/>
          </links>
        </score>
        <score clock=":52" points="1" quarter="3" type="extrapoint">
          <summary><![CDATA[4-S.Hauschka extra point is good.]]></summary>
          <links>
            <link href="/2014/REG/12/ARI/SEA/plays/f7a33351-144e-4f97-a803-e7fb198d5e27.xml" rel="summary" type="application/xml"/>
          </links>
        </score>
      </drive>
    </scoring_drives>
  </game>
  <game away="STL" clock=":00" completed="2014-11-24T00:16:30+00:00" home="SD" id="dd99429f-b4e8-4ac2-b54f-f3d8fce5c1e8" quarter="4" scheduled="2014-11-23T21:05:00+00:00" status="closed">
    <team id="SD" market="San Diego" name="Chargers" remaining_challenges="2" remaining_timeouts="2">
      <scoring points="27">
        <quarter number="1" points="3"/>
        <quarter number="2" points="3"/>
        <quarter number="3" points="14"/>
        <quarter number="4" points="7"/>
      </scoring>
    </team>
    <team id="STL" market="St. Louis" name="Rams" remaining_challenges="2" remaining_timeouts="2">
      <scoring points="24">
        <quarter number="1" points="3"/>
        <quarter number="2" points="7"/>
        <quarter number="3" points="7"/>
        <quarter number="4" points="7"/>
      </scoring>
    </team>
    <scoring_drives>
      <drive clock="11:40" quarter="1" sequence="1" team="SD">
        <score clock="09:14" points="3" quarter="1" type="fieldgoal">
          <summary><![CDATA[9-N.Novak 23 yards Field Goal is Good.]]></summary>
          <links>
            <link href="/2014/REG/12/STL/SD/plays/b3cdd752-5f00-4469-8819-040dff390951.xml" rel="summary" type="application/xml"/>
          </links>
        </score>
      </drive>
      <drive clock="09:10" quarter="1" sequence="2" team="STL">
        <score clock="01:07" points="3" quarter="1" type="fieldgoal">
          <summary><![CDATA[4-G.Zuerlein 22 yards Field Goal is Good.]]></summary>
          <links>
            <link href="/2014/REG/12/STL/SD/plays/764155c2-f6bd-4530-aefc-454901277262.xml" rel="summary" type="application/xml"/>
          </links>
        </score>
      </drive>
      <drive clock="01:03" quarter="1" sequence="3" team="SD">
        <score clock="11:48" points="6" quarter="2" type="touchdown">
          <summary><![CDATA[17-P.Rivers incomplete. Intended for 13-K.Allen, INTERCEPTED by 21-J.Jenkins at STL 1. 21-J.Jenkins runs 99 yards for a touchdown.]]></summary>
          <links>
            <link href="/2014/REG/12/STL/SD/plays/2eaace09-23be-46e3-9bfb-925c70c581fe.xml" rel="summary" type="application/xml"/>
          </links>
        </score>
      </drive>
      <drive clock="11:32" quarter="2" sequence="4" team="STL">
        <score clock="11:32" points="1" quarter="2" type="extrapoint">
          <summary><![CDATA[4-G.Zuerlein extra point is good.]]></summary>
          <links>
            <link href="/2014/REG/12/STL/SD/plays/2b24d971-f25e-45f3-b5c3-ce2632f9270e.xml" rel="summary" type="application/xml"/>
          </links>
        </score>
      </drive>
      <drive clock="01:33" quarter="2" sequence="5" team="SD">
        <score clock=":07" points="3" quarter="2" type="fieldgoal">
          <summary><![CDATA[9-N.Novak 48 yards Field Goal is Good.]]></summary>
          <links>
            <link href="/2014/REG/12/STL/SD/plays/5cd18b47-b57a-4592-b148-bb89cf8ffe39.xml" rel="summary" type="application/xml"/>
          </links>
        </score>
      </drive>
      <drive clock="12:39" quarter="3" sequence="6" team="SD">
        <score clock="09:59" points="6" quarter="3" type="touchdown">
          <summary><![CDATA[24-R.Mathews runs 32 yards for a touchdown.]]></summary>
          <links>
            <link href="/2014/REG/12/STL/SD/plays/a072650b-ba32-4cf8-9300-65ee88ddff7a.xml" rel="summary" type="application/xml"/>
          </links>
        </score>
        <score clock="09:50" points="1" quarter="3" type="extrapoint">
          <summary><![CDATA[9-N.Novak extra point is good.]]></summary>
          <links>
            <link href="/2014/REG/12/STL/SD/plays/9412468f-768c-42c1-a786-0f9f3d6b3bde.xml" rel="summary" type="application/xml"/>
          </links>
        </score>
      </drive>
      <drive clock="09:50" quarter="3" sequence="7" team="STL">
        <score clock="09:38" points="6" quarter="3" type="touchdown">
          <summary><![CDATA[14-S.Hill sacked at STL 13 for -7 yards, FUMBLES (94-C.Liuget). 59-A.Gachkar runs 13 yards for a touchdown.]]></summary>
          <links>
            <link href="/2014/REG/12/STL/SD/plays/da29bf08-d283-474d-94db-ae3c3c426bf8.xml" rel="summary" type="application/xml"/>
          </links>
        </score>
      </drive>
      <drive clock="09:29" quarter="3" sequence="8" team="SD">
        <score clock="09:29" points="1" quarter="3" type="extrapoint">
          <summary><![CDATA[9-N.Novak extra point is good.]]></summary>
          <links>
            <link href="/2014/REG/12/STL/SD/plays/40b630d8-0617-4c25-8cb9-f91dbb6b9b85.xml" rel="summary" type="application/xml"/>
          </links>
        </score>
      </drive>
      <drive clock="09:29" quarter="3" sequence="9" team="STL">
        <score clock="06:23" points="6" quarter="3" type="touchdown">
          <summary><![CDATA[11-T.Austin runs 6 yards for a touchdown.]]></summary>
          <links>
            <link href="/2014/REG/12/STL/SD/plays/f414b098-1eac-4e1e-ae7a-ff6c800804f5.xml" rel="summary" type="application/xml"/>
          </links>
        </score>
        <score clock="06:18" points="1" quarter="3" type="extrapoint">
          <summary><![CDATA[4-G.Zuerlein extra point is good.]]></summary>
          <links>
            <link href="/2014/REG/12/STL/SD/plays/16fde039-5325-48cf-9f7c-4463f45dc04a.xml" rel="summary" type="application/xml"/>
          </links>
        </score>
      </drive>
      <drive clock=":25" quarter="3" sequence="10" team="SD">
        <score clock="08:18" points="6" quarter="4" type="touchdown">
          <summary><![CDATA[17-P.Rivers complete to 13-K.Allen. 13-K.Allen runs 29 yards for a touchdown.]]></summary>
          <links>
            <link href="/2014/REG/12/STL/SD/plays/815548db-08cf-42bb-95dc-0b28a176678b.xml" rel="summary" type="application/xml"/>
          </links>
        </score>
        <score clock="08:09" points="1" quarter="4" type="extrapoint">
          <summary><![CDATA[9-N.Novak extra point is good.]]></summary>
          <links>
            <link href="/2014/REG/12/STL/SD/plays/639af99b-dc62-4e88-8d3b-52770faa96b2.xml" rel="summary" type="application/xml"/>
          </links>
        </score>
      </drive>
      <drive clock="08:09" quarter="4" sequence="11" team="STL">
        <score clock="02:09" points="6" quarter="4" type="touchdown">
          <summary><![CDATA[14-S.Hill complete to 12-S.Bailey. 12-S.Bailey runs 7 yards for a touchdown.]]></summary>
          <links>
            <link href="/2014/REG/12/STL/SD/plays/c2a355fd-5d67-4f2d-8dbc-913c31757bb3.xml" rel="summary" type="application/xml"/>
          </links>
        </score>
        <score clock="02:04" points="1" quarter="4" type="extrapoint">
          <summary><![CDATA[4-G.Zuerlein extra point is good.]]></summary>
          <links>
            <link href="/2014/REG/12/STL/SD/plays/fd2c00cb-02b7-42f6-9e9b-eb37ee892710.xml" rel="summary" type="application/xml"/>
          </links>
        </score>
      </drive>
    </scoring_drives>
  </game>
<!--Generation finished at 2015-06-29 15:05:30 +0000--></games>
