<?xml version="1.0"?>
<games season="2013" type="REG" week="6" xmlns="http://feed.elasticstats.com/schema/nfl/boxscore-v1.0.xsd"><!--Generation started at 2014-08-27 20:26:58 +0000-->  <game away="TEN" clock=":00" completed="2013-10-13T22:56:54+00:00" home="SEA" id="80635d24-4fb4-4b8a-ba6c-fabe6a545eef" quarter="4" scheduled="2013-10-13T20:05:00+00:00" status="closed">
    <team id="SEA" market="Seattle" name="Seahawks" remaining_challenges="1" remaining_timeouts="2">
      <scoring points="20">
        <quarter number="1" points="0"/>
        <quarter number="2" points="7"/>
        <quarter number="3" points="3"/>
        <quarter number="4" points="10"/>
      </scoring>
    </team>
    <team id="TEN" market="Tennessee" name="Titans" remaining_challenges="2" remaining_timeouts="2">
      <scoring points="13">
        <quarter number="1" points="3"/>
        <quarter number="2" points="7"/>
        <quarter number="3" points="0"/>
        <quarter number="4" points="3"/>
      </scoring>
    </team>
    <scoring_drives>
      <drive clock="09:59" quarter="1" sequence="1" team="TEN">
        <score clock="05:21" points="3" quarter="1" type="fieldgoal">
          <summary><![CDATA[2-R.Bironas 38 yards Field Goal is Good.]]></summary>
          <links>
            <link href="/2013/REG/6/TEN/SEA/plays/37d2cb60-718b-43c3-8be4-43e11b32f59d.xml" rel="summary" type="application/xml"/>
          </links>
        </score>
      </drive>
      <drive clock="09:23" quarter="2" sequence="2" team="SEA">
        <score clock="02:46" points="6" quarter="2" type="touchdown">
          <summary><![CDATA[24-M.Lynch runs 1 yard for a touchdown.]]></summary>
          <links>
            <link href="/2013/REG/6/TEN/SEA/plays/6bb71386-b7ed-4ddb-a25b-957bb08ad331.xml" rel="summary" type="application/xml"/>
          </links>
        </score>
        <score clock="02:41" points="1" quarter="2" type="extrapoint">
          <summary><![CDATA[4-S.Hauschka extra point is good.]]></summary>
          <links>
            <link href="/2013/REG/6/TEN/SEA/plays/5cd9d76e-65f3-4ed1-bf02-d93da5cad334.xml" rel="summary" type="application/xml"/>
          </links>
        </score>
      </drive>
      <drive clock=":54" quarter="2" sequence="3" team="SEA">
        <score clock=":02" points="6" quarter="2" type="touchdown">
          <summary><![CDATA[42-C.Maragos FUMBLES (Aborted) at TEN 12. Downed at the TEN 12 42-C.Maragos to TEN 16, FUMBLES (33-M.Griffin). 30-J.McCourty runs 77 yards for a touchdown.]]></summary>
          <links>
            <link href="/2013/REG/6/TEN/SEA/plays/4bf645fa-51b4-45d7-9495-cf87ed4470b1.xml" rel="summary" type="application/xml"/>
          </links>
        </score>
      </drive>
      <drive clock=":00" quarter="2" sequence="4" team="TEN">
        <score clock=":00" points="1" quarter="2" type="extrapoint">
          <summary><![CDATA[2-R.Bironas extra point is good.]]></summary>
          <links>
            <link href="/2013/REG/6/TEN/SEA/plays/27b24021-3dac-4bac-8c67-455386dae831.xml" rel="summary" type="application/xml"/>
          </links>
        </score>
      </drive>
      <drive clock="10:53" quarter="3" sequence="5" team="SEA">
        <score clock="04:31" points="3" quarter="3" type="fieldgoal">
          <summary><![CDATA[4-S.Hauschka 31 yards Field Goal is Good.]]></summary>
          <links>
            <link href="/2013/REG/6/TEN/SEA/plays/0e18b944-296f-4df1-a820-941a4192119b.xml" rel="summary" type="application/xml"/>
          </links>
        </score>
      </drive>
      <drive clock="15:00" quarter="4" sequence="6" team="SEA">
        <score clock="11:26" points="3" quarter="4" type="fieldgoal">
          <summary><![CDATA[4-S.Hauschka 29 yards Field Goal is Good.]]></summary>
          <links>
            <link href="/2013/REG/6/TEN/SEA/plays/33948703-56df-475d-9c77-e820287d1343.xml" rel="summary" type="application/xml"/>
          </links>
        </score>
      </drive>
      <drive clock="11:15" quarter="4" sequence="7" team="SEA">
        <score clock="07:37" points="6" quarter="4" type="touchdown">
          <summary><![CDATA[24-M.Lynch runs 3 yards for a touchdown.]]></summary>
          <links>
            <link href="/2013/REG/6/TEN/SEA/plays/92dff611-f5f1-4815-b239-4cd869543025.xml" rel="summary" type="application/xml"/>
          </links>
        </score>
        <score clock="07:33" points="1" quarter="4" type="extrapoint">
          <summary><![CDATA[4-S.Hauschka extra point is good.]]></summary>
          <links>
            <link href="/2013/REG/6/TEN/SEA/plays/9c2bd92f-43d6-4417-9746-485b60277cfe.xml" rel="summary" type="application/xml"/>
          </links>
        </score>
      </drive>
      <drive clock="07:33" quarter="4" sequence="8" team="TEN">
        <score clock="02:21" points="3" quarter="4" type="fieldgoal">
          <summary><![CDATA[2-R.Bironas 25 yards Field Goal is Good.]]></summary>
          <links>
            <link href="/2013/REG/6/TEN/SEA/plays/f2683cf3-234f-4159-9efc-0cd6b6469cf9.xml" rel="summary" type="application/xml"/>
          </links>
        </score>
      </drive>
    </scoring_drives>
  </game>
  <game away="OAK" clock=":00" completed="2013-10-13T20:19:41+00:00" home="KC" id="84765c33-3678-4354-b722-a8b804f65b1b" quarter="4" scheduled="2013-10-13T17:00:00+00:00" status="closed">
    <team id="KC" market="Kansas City" name="Chiefs" remaining_challenges="2" remaining_timeouts="2">
      <scoring points="24">
        <quarter number="1" points="0"/>
        <quarter number="2" points="7"/>
        <quarter number="3" points="7"/>
        <quarter number="4" points="10"/>
      </scoring>
    </team>
    <team id="OAK" market="Oakland" name="Raiders" remaining_challenges="2" remaining_timeouts="2">
      <scoring points="7">
        <quarter number="1" points="0"/>
        <quarter number="2" points="7"/>
        <quarter number="3" points="0"/>
        <quarter number="4" points="0"/>
      </scoring>
    </team>
    <scoring_drives>
      <drive clock="11:56" quarter="2" sequence="1" team="OAK">
        <score clock="08:48" points="6" quarter="2" type="touchdown">
          <summary><![CDATA[2-T. Pryor complete to 17-D.Moore. 17-D.Moore runs 39 yards for a touchdown.]]></summary>
          <links>
            <link href="/2013/REG/6/OAK/KC/plays/a58fca81-5893-44a9-a285-fb28d093f096.xml" rel="summary" type="application/xml"/>
          </links>
        </score>
        <score clock="08:40" points="1" quarter="2" type="extrapoint">
          <summary><![CDATA[11-S.Janikowski extra point is good.]]></summary>
          <links>
            <link href="/2013/REG/6/OAK/KC/plays/fbc4290e-8345-4b0f-bdce-f4ee291debe8.xml" rel="summary" type="application/xml"/>
          </links>
        </score>
      </drive>
      <drive clock="02:09" quarter="2" sequence="2" team="KC">
        <score clock="01:12" points="6" quarter="2" type="touchdown">
          <summary><![CDATA[25-J.Charles runs 7 yards for a touchdown.]]></summary>
          <links>
            <link href="/2013/REG/6/OAK/KC/plays/780b5302-18a9-4e81-8646-d8c628542986.xml" rel="summary" type="application/xml"/>
          </links>
        </score>
        <score clock="01:06" points="1" quarter="2" type="extrapoint">
          <summary><![CDATA[6-R.Succop extra point is good.]]></summary>
          <links>
            <link href="/2013/REG/6/OAK/KC/plays/e7a0b6df-87f3-48fd-874c-752a331d0e12.xml" rel="summary" type="application/xml"/>
          </links>
        </score>
      </drive>
      <drive clock="03:57" quarter="3" sequence="3" team="KC">
        <score clock="02:07" points="6" quarter="3" type="touchdown">
          <summary><![CDATA[25-J.Charles runs 2 yards for a touchdown.]]></summary>
          <links>
            <link href="/2013/REG/6/OAK/KC/plays/ff96458d-c0e8-4164-b75b-2ca22f161d47.xml" rel="summary" type="application/xml"/>
          </links>
        </score>
        <score clock="02:01" points="1" quarter="3" type="extrapoint">
          <summary><![CDATA[6-R.Succop extra point is good.]]></summary>
          <links>
            <link href="/2013/REG/6/OAK/KC/plays/4e6f1d94-68e6-48e5-a0c8-f06fad2c650e.xml" rel="summary" type="application/xml"/>
          </links>
        </score>
      </drive>
      <drive clock="04:09" quarter="4" sequence="4" team="KC">
        <score clock="02:13" points="3" quarter="4" type="fieldgoal">
          <summary><![CDATA[6-R.Succop 33 yards Field Goal is Good.]]></summary>
          <links>
            <link href="/2013/REG/6/OAK/KC/plays/55f181da-ec12-4317-849d-3ecb3b9ee2bc.xml" rel="summary" type="application/xml"/>
          </links>
        </score>
      </drive>
      <drive clock="02:09" quarter="4" sequence="5" team="OAK">
        <score clock="01:45" points="6" quarter="4" type="touchdown">
          <summary><![CDATA[2-T. Pryor incomplete. Intended for 81-M.Rivera, INTERCEPTED by 39-H.Abdullah at OAK 44. 39-H.Abdullah runs 44 yards for a touchdown.]]></summary>
          <links>
            <link href="/2013/REG/6/OAK/KC/plays/80dfe28c-9f01-46ee-a443-014e9db4695e.xml" rel="summary" type="application/xml"/>
          </links>
        </score>
      </drive>
      <drive clock="01:35" quarter="4" sequence="6" team="KC">
        <score clock="01:35" points="1" quarter="4" type="extrapoint">
          <summary><![CDATA[6-R.Succop extra point is good.]]></summary>
          <links>
            <link href="/2013/REG/6/OAK/KC/plays/5f951f7f-d843-45a9-8083-8112e5e871dd.xml" rel="summary" type="application/xml"/>
          </links>
        </score>
      </drive>
    </scoring_drives>
  </game>
  <game away="CIN" clock=":00" completed="2013-10-13T20:22:18+00:00" home="BUF" id="6e154e97-b99d-40d7-8f3d-fd9cb09d2c45" quarter="5" scheduled="2013-10-13T17:00:00+00:00" status="closed">
    <team id="BUF" market="Buffalo" name="Bills" remaining_challenges="2" remaining_timeouts="2">
      <scoring points="24">
        <quarter number="1" points="7"/>
        <quarter number="2" points="3"/>
        <quarter number="3" points="0"/>
        <quarter number="4" points="14"/>
        <quarter number="5" points="0"/>
      </scoring>
    </team>
    <team id="CIN" market="Cincinnati" name="Bengals" remaining_challenges="2" remaining_timeouts="2">
      <scoring points="27">
        <quarter number="1" points="10"/>
        <quarter number="2" points="7"/>
        <quarter number="3" points="7"/>
        <quarter number="4" points="0"/>
        <quarter number="5" points="3"/>
      </scoring>
    </team>
    <scoring_drives>
      <drive clock="15:00" quarter="1" sequence="1" team="CIN">
        <score clock="12:19" points="3" quarter="1" type="fieldgoal">
          <summary><![CDATA[2-M.Nugent 46 yards Field Goal is Good.]]></summary>
          <links>
            <link href="/2013/REG/6/CIN/BUF/plays/e4ca1af6-4483-4916-999f-214f700dc686.xml" rel="summary" type="application/xml"/>
          </links>
        </score>
      </drive>
      <drive clock="12:14" quarter="1" sequence="2" team="BUF">
        <score clock="10:05" points="6" quarter="1" type="touchdown">
          <summary><![CDATA[9-T.Lewis scrambles to the runs 3 yards for a touchdown.]]></summary>
          <links>
            <link href="/2013/REG/6/CIN/BUF/plays/45099540-118b-429b-8c5e-471f6becde38.xml" rel="summary" type="application/xml"/>
          </links>
        </score>
        <score clock="10:01" points="1" quarter="1" type="extrapoint">
          <summary><![CDATA[2-D.Carpenter extra point is good.]]></summary>
          <links>
            <link href="/2013/REG/6/CIN/BUF/plays/ce2db680-e893-4849-a745-67fd0a430d62.xml" rel="summary" type="application/xml"/>
          </links>
        </score>
      </drive>
      <drive clock="10:01" quarter="1" sequence="3" team="CIN">
        <score clock="05:32" points="6" quarter="1" type="touchdown">
          <summary><![CDATA[14-A.Dalton complete to 18-A.Green. 18-A.Green runs 18 yards for a touchdown.]]></summary>
          <links>
            <link href="/2013/REG/6/CIN/BUF/plays/e8e8079c-1c46-4c65-8d22-3de02a8dc4f6.xml" rel="summary" type="application/xml"/>
          </links>
        </score>
        <score clock="05:26" points="1" quarter="1" type="extrapoint">
          <summary><![CDATA[2-M.Nugent extra point is good.]]></summary>
          <links>
            <link href="/2013/REG/6/CIN/BUF/plays/bea9d35d-768e-424f-9ca6-883698c7a5df.xml" rel="summary" type="application/xml"/>
          </links>
        </score>
      </drive>
      <drive clock="13:41" quarter="2" sequence="4" team="CIN">
        <score clock="08:42" points="6" quarter="2" type="touchdown">
          <summary><![CDATA[14-A.Dalton complete to 25-G.Bernard. 25-G.Bernard runs 20 yards for a touchdown.]]></summary>
          <links>
            <link href="/2013/REG/6/CIN/BUF/plays/4a854a58-b2ea-4430-800b-116199a32b7a.xml" rel="summary" type="application/xml"/>
          </links>
        </score>
        <score clock="08:34" points="1" quarter="2" type="extrapoint">
          <summary><![CDATA[2-M.Nugent extra point is good.]]></summary>
          <links>
            <link href="/2013/REG/6/CIN/BUF/plays/06a233d4-0c69-4bab-8c99-e2c86904afa7.xml" rel="summary" type="application/xml"/>
          </links>
        </score>
      </drive>
      <drive clock="08:34" quarter="2" sequence="5" team="BUF">
        <score clock="04:19" points="3" quarter="2" type="fieldgoal">
          <summary><![CDATA[2-D.Carpenter 51 yards Field Goal is Good.]]></summary>
          <links>
            <link href="/2013/REG/6/CIN/BUF/plays/1e2015d0-de5e-44c5-b294-113978de92e5.xml" rel="summary" type="application/xml"/>
          </links>
        </score>
      </drive>
      <drive clock="13:40" quarter="3" sequence="6" team="CIN">
        <score clock="10:49" points="6" quarter="3" type="touchdown">
          <summary><![CDATA[14-A.Dalton complete to 82-M.Jones. 82-M.Jones runs 10 yards for a touchdown.]]></summary>
          <links>
            <link href="/2013/REG/6/CIN/BUF/plays/1593c88c-5c70-44cb-a2f2-abb9016b4c80.xml" rel="summary" type="application/xml"/>
          </links>
        </score>
        <score clock="10:46" points="1" quarter="3" type="extrapoint">
          <summary><![CDATA[2-M.Nugent extra point is good.]]></summary>
          <links>
            <link href="/2013/REG/6/CIN/BUF/plays/4c1188de-08aa-4124-8bbb-4d1475d1a025.xml" rel="summary" type="application/xml"/>
          </links>
        </score>
      </drive>
      <drive clock="12:46" quarter="4" sequence="7" team="BUF">
        <score clock="10:17" points="6" quarter="4" type="touchdown">
          <summary><![CDATA[9-T.Lewis complete to 84-S.Chandler. 84-S.Chandler runs 22 yards for a touchdown.]]></summary>
          <links>
            <link href="/2013/REG/6/CIN/BUF/plays/e2ae2c26-8dd9-478a-8f74-9e791ab14fdf.xml" rel="summary" type="application/xml"/>
          </links>
        </score>
        <score clock="10:13" points="1" quarter="4" type="extrapoint">
          <summary><![CDATA[2-D.Carpenter extra point is good.]]></summary>
          <links>
            <link href="/2013/REG/6/CIN/BUF/plays/04abedf0-dc8a-454f-a593-1f576f1f0c0d.xml" rel="summary" type="application/xml"/>
          </links>
        </score>
      </drive>
      <drive clock="02:40" quarter="4" sequence="8" team="BUF">
        <score clock="01:15" points="6" quarter="4" type="touchdown">
          <summary><![CDATA[9-T.Lewis complete to 88-M.Goodwin. 88-M.Goodwin runs 40 yards for a touchdown.]]></summary>
          <links>
            <link href="/2013/REG/6/CIN/BUF/plays/ac97941a-8e83-4c4d-8d1d-5cccee54da46.xml" rel="summary" type="application/xml"/>
          </links>
        </score>
        <score clock="01:08" points="1" quarter="4" type="extrapoint">
          <summary><![CDATA[2-D.Carpenter extra point is good.]]></summary>
          <links>
            <link href="/2013/REG/6/CIN/BUF/plays/ee4f0539-b7cf-4db2-bcee-6dc27cb63cdc.xml" rel="summary" type="application/xml"/>
          </links>
        </score>
      </drive>
      <drive clock="08:48" quarter="5" sequence="9" team="CIN">
        <score clock="06:44" points="3" quarter="5" type="fieldgoal">
          <summary><![CDATA[2-M.Nugent 43 yards Field Goal is Good.]]></summary>
          <links>
            <link href="/2013/REG/6/CIN/BUF/plays/05c2682e-c9c6-4192-add5-182fc6d73157.xml" rel="summary" type="application/xml"/>
          </links>
        </score>
      </drive>
    </scoring_drives>
  </game>
  <game away="JAC" clock=":00" completed="2013-10-13T23:05:55+00:00" home="DEN" id="9c74acd7-257d-4d87-8b97-4855fe2b6304" quarter="4" scheduled="2013-10-13T20:05:00+00:00" status="closed">
    <team id="DEN" market="Denver" name="Broncos" remaining_challenges="1" remaining_timeouts="2">
      <scoring points="35">
        <quarter number="1" points="14"/>
        <quarter number="2" points="0"/>
        <quarter number="3" points="14"/>
        <quarter number="4" points="7"/>
      </scoring>
    </team>
    <team id="JAC" market="Jacksonville" name="Jaguars" remaining_challenges="2" remaining_timeouts="2">
      <scoring points="19">
        <quarter number="1" points="0"/>
        <quarter number="2" points="12"/>
        <quarter number="3" points="7"/>
        <quarter number="4" points="0"/>
      </scoring>
    </team>
    <scoring_drives>
      <drive clock="14:11" quarter="1" sequence="1" team="DEN">
        <score clock="12:14" points="6" quarter="1" type="touchdown">
          <summary><![CDATA[18-P.Manning complete to 80-J.Thomas. 80-J.Thomas runs 3 yards for a touchdown.]]></summary>
          <links>
            <link href="/2013/REG/6/JAC/DEN/plays/ae0c5db1-efce-41b0-bad4-e4efb5772f03.xml" rel="summary" type="application/xml"/>
          </links>
        </score>
        <score clock="12:25" points="1" quarter="1" type="extrapoint">
          <summary><![CDATA[5-M.Prater extra point is good.]]></summary>
          <links>
            <link href="/2013/REG/6/JAC/DEN/plays/6df24b50-f1a0-470b-b35a-0216963075ae.xml" rel="summary" type="application/xml"/>
          </links>
        </score>
      </drive>
      <drive clock="08:52" quarter="1" sequence="2" team="DEN">
        <score clock="02:50" points="6" quarter="1" type="touchdown">
          <summary><![CDATA[18-P.Manning complete to 83-W.Welker. 83-W.Welker runs 20 yards for a touchdown.]]></summary>
          <links>
            <link href="/2013/REG/6/JAC/DEN/plays/4dae3d95-b417-4be8-809c-ac73ecdc1b62.xml" rel="summary" type="application/xml"/>
          </links>
        </score>
        <score clock="02:44" points="1" quarter="1" type="extrapoint">
          <summary><![CDATA[5-M.Prater extra point is good.]]></summary>
          <links>
            <link href="/2013/REG/6/JAC/DEN/plays/43698893-1e16-433f-8308-b3d8c44400fb.xml" rel="summary" type="application/xml"/>
          </links>
        </score>
      </drive>
      <drive clock="02:44" quarter="1" sequence="3" team="JAC">
        <score clock="13:24" points="3" quarter="2" type="fieldgoal">
          <summary><![CDATA[10-J.Scobee 50 yards Field Goal is Good.]]></summary>
          <links>
            <link href="/2013/REG/6/JAC/DEN/plays/edb1edec-0609-4ccd-ad08-66c558b039f2.xml" rel="summary" type="application/xml"/>
          </links>
        </score>
      </drive>
      <drive clock="08:03" quarter="2" sequence="4" team="JAC">
        <score clock="05:48" points="3" quarter="2" type="fieldgoal">
          <summary><![CDATA[10-J.Scobee 30 yards Field Goal is Good.]]></summary>
          <links>
            <link href="/2013/REG/6/JAC/DEN/plays/59018e29-de99-4f90-bb4f-9e79fec15c45.xml" rel="summary" type="application/xml"/>
          </links>
        </score>
      </drive>
      <drive clock="01:14" quarter="2" sequence="5" team="DEN">
        <score clock=":48" points="6" quarter="2" type="touchdown">
          <summary><![CDATA[18-P.Manning incomplete. Intended for 83-W.Welker, INTERCEPTED by 51-P.Posluszny at JAC 41. 51-P.Posluszny runs 59 yards for a touchdown.]]></summary>
          <links>
            <link href="/2013/REG/6/JAC/DEN/plays/205f7a8e-a18d-4e74-b7e0-4be9b95f0151.xml" rel="summary" type="application/xml"/>
          </links>
        </score>
      </drive>
      <drive clock="15:00" quarter="3" sequence="6" team="DEN">
        <score clock="12:18" points="6" quarter="3" type="touchdown">
          <summary><![CDATA[27-K.Moreno runs 1 yard for a touchdown.]]></summary>
          <links>
            <link href="/2013/REG/6/JAC/DEN/plays/db4ab24f-5361-4c8f-8a56-a7c38b7a92d2.xml" rel="summary" type="application/xml"/>
          </links>
        </score>
        <score clock="12:16" points="1" quarter="3" type="extrapoint">
          <summary><![CDATA[5-M.Prater extra point is good.]]></summary>
          <links>
            <link href="/2013/REG/6/JAC/DEN/plays/ef41ca28-9d74-4477-b06b-7365d0294538.xml" rel="summary" type="application/xml"/>
          </links>
        </score>
      </drive>
      <drive clock="12:16" quarter="3" sequence="7" team="JAC">
        <score clock="07:50" points="6" quarter="3" type="touchdown">
          <summary><![CDATA[32-M.Jones-Drew runs 5 yards for a touchdown.]]></summary>
          <links>
            <link href="/2013/REG/6/JAC/DEN/plays/18d952ae-e55d-4e2c-9f8b-bf8c281ea49b.xml" rel="summary" type="application/xml"/>
          </links>
        </score>
        <score clock="07:43" points="1" quarter="3" type="extrapoint">
          <summary><![CDATA[10-J.Scobee extra point is good.]]></summary>
          <links>
            <link href="/2013/REG/6/JAC/DEN/plays/7b78cdbc-0585-49d5-8cc2-5b6cdf850661.xml" rel="summary" type="application/xml"/>
          </links>
        </score>
      </drive>
      <drive clock="07:43" quarter="3" sequence="8" team="DEN">
        <score clock="04:07" points="6" quarter="3" type="touchdown">
          <summary><![CDATA[27-K.Moreno runs 8 yards for a touchdown.]]></summary>
          <links>
            <link href="/2013/REG/6/JAC/DEN/plays/e4cdc29c-94d4-4311-8387-f057a9d70298.xml" rel="summary" type="application/xml"/>
          </links>
        </score>
        <score clock="04:02" points="1" quarter="3" type="extrapoint">
          <summary><![CDATA[5-M.Prater extra point is good.]]></summary>
          <links>
            <link href="/2013/REG/6/JAC/DEN/plays/6a7d6565-d2e7-49f7-b7ef-bbbd0ed829d3.xml" rel="summary" type="application/xml"/>
          </links>
        </score>
      </drive>
      <drive clock="11:28" quarter="4" sequence="9" team="DEN">
        <score clock="09:13" points="6" quarter="4" type="touchdown">
          <summary><![CDATA[27-K.Moreno runs 3 yards for a touchdown.]]></summary>
          <links>
            <link href="/2013/REG/6/JAC/DEN/plays/fb660a5e-092f-414e-aced-35f4db551a79.xml" rel="summary" type="application/xml"/>
          </links>
        </score>
        <score clock="09:09" points="1" quarter="4" type="extrapoint">
          <summary><![CDATA[5-M.Prater extra point is good.]]></summary>
          <links>
            <link href="/2013/REG/6/JAC/DEN/plays/9d0c10c5-f702-4a29-b608-dd7a50a517ea.xml" rel="summary" type="application/xml"/>
          </links>
        </score>
      </drive>
    </scoring_drives>
  </game>
  <game away="GB" clock=":00" completed="2013-10-13T20:10:29+00:00" home="BAL" id="eb289b02-1f84-4e9d-9085-749eba939a04" quarter="4" scheduled="2013-10-13T17:00:00+00:00" status="closed">
    <team id="BAL" market="Baltimore" name="Ravens" remaining_challenges="2" remaining_timeouts="2">
      <scoring points="17">
        <quarter number="1" points="0"/>
        <quarter number="2" points="0"/>
        <quarter number="3" points="3"/>
        <quarter number="4" points="14"/>
      </scoring>
    </team>
    <team id="GB" market="Green Bay" name="Packers" remaining_challenges="2" remaining_timeouts="2">
      <scoring points="19">
        <quarter number="1" points="3"/>
        <quarter number="2" points="3"/>
        <quarter number="3" points="10"/>
        <quarter number="4" points="3"/>
      </scoring>
    </team>
    <scoring_drives>
      <drive clock="15:00" quarter="1" sequence="1" team="GB">
        <score clock="13:16" points="3" quarter="1" type="fieldgoal">
          <summary><![CDATA[2-M.Crosby 46 yards Field Goal is Good.]]></summary>
          <links>
            <link href="/2013/REG/6/GB/BAL/plays/d25c2677-4b2c-4fe2-8782-92472dd443df.xml" rel="summary" type="application/xml"/>
          </links>
        </score>
      </drive>
      <drive clock=":02" quarter="2" sequence="2" team="GB">
        <score clock=":02" points="3" quarter="2" type="fieldgoal">
          <summary><![CDATA[2-M.Crosby 31 yards Field Goal is Good.]]></summary>
          <links>
            <link href="/2013/REG/6/GB/BAL/plays/d25bf55c-429b-4042-9987-4257dc2c7c34.xml" rel="summary" type="application/xml"/>
          </links>
        </score>
      </drive>
      <drive clock="09:10" quarter="3" sequence="3" team="GB">
        <score clock="06:11" points="3" quarter="3" type="fieldgoal">
          <summary><![CDATA[2-M.Crosby 50 yards Field Goal is Good.]]></summary>
          <links>
            <link href="/2013/REG/6/GB/BAL/plays/01e5bc22-5363-4f17-bd00-d1ec8e3674ea.xml" rel="summary" type="application/xml"/>
          </links>
        </score>
      </drive>
      <drive clock="06:06" quarter="3" sequence="4" team="BAL">
        <score clock="04:38" points="3" quarter="3" type="fieldgoal">
          <summary><![CDATA[9-J.Tucker 23 yards Field Goal is Good.]]></summary>
          <links>
            <link href="/2013/REG/6/GB/BAL/plays/46daa898-0f25-4b23-a3ee-6b301a8391bc.xml" rel="summary" type="application/xml"/>
          </links>
        </score>
      </drive>
      <drive clock="04:34" quarter="3" sequence="5" team="GB">
        <score clock="02:23" points="6" quarter="3" type="touchdown">
          <summary><![CDATA[12-A.Rodgers complete to 87-J.Nelson. 87-J.Nelson runs 64 yards for a touchdown.]]></summary>
          <links>
            <link href="/2013/REG/6/GB/BAL/plays/c905e0ac-1a6b-47a5-b84a-dfe9fa2b33eb.xml" rel="summary" type="application/xml"/>
          </links>
        </score>
        <score clock="02:12" points="1" quarter="3" type="extrapoint">
          <summary><![CDATA[2-M.Crosby extra point is good.]]></summary>
          <links>
            <link href="/2013/REG/6/GB/BAL/plays/133619ba-b1bf-45ec-870f-9bf984aa0017.xml" rel="summary" type="application/xml"/>
          </links>
        </score>
      </drive>
      <drive clock="02:12" quarter="3" sequence="6" team="BAL">
        <score clock="11:59" points="6" quarter="4" type="touchdown">
          <summary><![CDATA[5-J.Flacco complete to 12-J.Jones. 12-J.Jones runs 11 yards for a touchdown.]]></summary>
          <links>
            <link href="/2013/REG/6/GB/BAL/plays/fa95a624-f207-488a-ae86-24a1f86ece4a.xml" rel="summary" type="application/xml"/>
          </links>
        </score>
        <score clock="11:52" points="1" quarter="4" type="extrapoint">
          <summary><![CDATA[9-J.Tucker extra point is good.]]></summary>
          <links>
            <link href="/2013/REG/6/GB/BAL/plays/ac83e4d6-38fb-4581-9a1c-02ed53b56efb.xml" rel="summary" type="application/xml"/>
          </links>
        </score>
      </drive>
      <drive clock="11:52" quarter="4" sequence="7" team="GB">
        <score clock="04:20" points="3" quarter="4" type="fieldgoal">
          <summary><![CDATA[2-M.Crosby 31 yards Field Goal is Good.]]></summary>
          <links>
            <link href="/2013/REG/6/GB/BAL/plays/4d723efc-d255-469b-a736-a46965961a5d.xml" rel="summary" type="application/xml"/>
          </links>
        </score>
      </drive>
      <drive clock="04:17" quarter="4" sequence="8" team="BAL">
        <score clock="02:10" points="6" quarter="4" type="touchdown">
          <summary><![CDATA[5-J.Flacco complete to 87-D.Clark. 87-D.Clark runs 18 yards for a touchdown.]]></summary>
          <links>
            <link href="/2013/REG/6/GB/BAL/plays/eba350a5-50e6-4228-95ca-0c6dbca65e73.xml" rel="summary" type="application/xml"/>
          </links>
        </score>
        <score clock="02:04" points="1" quarter="4" type="extrapoint">
          <summary><![CDATA[9-J.Tucker extra point is good.]]></summary>
          <links>
            <link href="/2013/REG/6/GB/BAL/plays/10a43194-a329-48a3-86ed-be487d287d79.xml" rel="summary" type="application/xml"/>
          </links>
        </score>
      </drive>
    </scoring_drives>
  </game>
  <game away="ARI" clock=":00" completed="2013-10-13T23:56:45+00:00" home="SF" id="46f17fa4-f2ef-41ef-9ede-00929c043ebe" quarter="4" scheduled="2013-10-13T20:25:00+00:00" status="closed">
    <team id="SF" market="San Francisco" name="49ers" remaining_challenges="0" remaining_timeouts="2">
      <scoring points="32">
        <quarter number="1" points="6"/>
        <quarter number="2" points="16"/>
        <quarter number="3" points="0"/>
        <quarter number="4" points="10"/>
      </scoring>
    </team>
    <team id="ARI" market="Arizona" name="Cardinals" remaining_challenges="2" remaining_timeouts="2">
      <scoring points="20">
        <quarter number="1" points="7"/>
        <quarter number="2" points="7"/>
        <quarter number="3" points="6"/>
        <quarter number="4" points="0"/>
      </scoring>
    </team>
    <scoring_drives>
      <drive clock="10:37" quarter="1" sequence="1" team="SF">
        <score clock="09:41" points="3" quarter="1" type="fieldgoal">
          <summary><![CDATA[9-P.Dawson 35 yards Field Goal is Good.]]></summary>
          <links>
            <link href="/2013/REG/6/ARI/SF/plays/16aa7e4b-566e-4281-a57a-0d6eab48b9cd.xml" rel="summary" type="application/xml"/>
          </links>
        </score>
      </drive>
      <drive clock="06:06" quarter="1" sequence="2" team="SF">
        <score clock="04:36" points="3" quarter="1" type="fieldgoal">
          <summary><![CDATA[9-P.Dawson 25 yards Field Goal is Good.]]></summary>
          <links>
            <link href="/2013/REG/6/ARI/SF/plays/42040cbf-faec-4a09-afe3-c49ac6028a0d.xml" rel="summary" type="application/xml"/>
          </links>
        </score>
      </drive>
      <drive clock="04:31" quarter="1" sequence="3" team="ARI">
        <score clock="03:18" points="6" quarter="1" type="touchdown">
          <summary><![CDATA[3-C.Palmer complete to 11-L.Fitzgerald. 11-L.Fitzgerald runs 75 yards for a touchdown.]]></summary>
          <links>
            <link href="/2013/REG/6/ARI/SF/plays/9a0b1a46-e502-4050-9c53-34fdc6922928.xml" rel="summary" type="application/xml"/>
          </links>
        </score>
        <score clock="03:06" points="1" quarter="1" type="extrapoint">
          <summary><![CDATA[4-J.Feely extra point is good.]]></summary>
          <links>
            <link href="/2013/REG/6/ARI/SF/plays/0050d736-5cfd-425e-9dd5-e55e60011ba6.xml" rel="summary" type="application/xml"/>
          </links>
        </score>
      </drive>
      <drive clock="11:09" quarter="2" sequence="4" team="ARI">
        <score clock="09:26" points="2" quarter="2" type="safety">
          <summary><![CDATA[3-C.Palmer sacked at ARI End Zone for -4 yards to ARI End Zone for no gain, safety (96-C.Lemonier).]]></summary>
          <links>
            <link href="/2013/REG/6/ARI/SF/plays/7848f313-2927-44ad-ab59-d16cf7a2f122.xml" rel="summary" type="application/xml"/>
          </links>
        </score>
      </drive>
      <drive clock="09:22" quarter="2" sequence="5" team="SF">
        <score clock="08:41" points="6" quarter="2" type="touchdown">
          <summary><![CDATA[7-C.Kaepernick complete to 85-V.Davis. 85-V.Davis runs 61 yards for a touchdown. Penalty on ARI 66-A.Ta'amu, Offside, declined.]]></summary>
          <links>
            <link href="/2013/REG/6/ARI/SF/plays/10aad959-e7fa-4fd4-ad8d-3700817c699a.xml" rel="summary" type="application/xml"/>
          </links>
        </score>
        <score clock="08:31" points="1" quarter="2" type="extrapoint">
          <summary><![CDATA[9-P.Dawson extra point is good.]]></summary>
          <links>
            <link href="/2013/REG/6/ARI/SF/plays/359f0a9a-b6b8-45b5-b85d-0b47200a2073.xml" rel="summary" type="application/xml"/>
          </links>
        </score>
      </drive>
      <drive clock="08:31" quarter="2" sequence="6" team="ARI">
        <score clock="07:08" points="6" quarter="2" type="touchdown">
          <summary><![CDATA[38-A.Ellington runs 15 yards for a touchdown.]]></summary>
          <links>
            <link href="/2013/REG/6/ARI/SF/plays/639d388b-0d91-40cd-bbfe-24fd87bfca6c.xml" rel="summary" type="application/xml"/>
          </links>
        </score>
        <score clock="07:03" points="1" quarter="2" type="extrapoint">
          <summary><![CDATA[4-J.Feely extra point is good.]]></summary>
          <links>
            <link href="/2013/REG/6/ARI/SF/plays/7af049a6-212c-4adc-b429-582d06e90276.xml" rel="summary" type="application/xml"/>
          </links>
        </score>
      </drive>
      <drive clock="02:54" quarter="2" sequence="7" team="SF">
        <score clock="02:00" points="6" quarter="2" type="touchdown">
          <summary><![CDATA[7-C.Kaepernick complete to 85-V.Davis. 85-V.Davis runs 35 yards for a touchdown.]]></summary>
          <links>
            <link href="/2013/REG/6/ARI/SF/plays/890560ce-2cf6-408f-9750-fa5998ab8458.xml" rel="summary" type="application/xml"/>
          </links>
        </score>
        <score clock="01:55" points="1" quarter="2" type="extrapoint">
          <summary><![CDATA[9-P.Dawson extra point is good.]]></summary>
          <links>
            <link href="/2013/REG/6/ARI/SF/plays/1d652235-c72f-45c8-952f-658559a1dfce.xml" rel="summary" type="application/xml"/>
          </links>
        </score>
      </drive>
      <drive clock="12:45" quarter="3" sequence="8" team="ARI">
        <score clock="08:18" points="6" quarter="3" type="touchdown">
          <summary><![CDATA[3-C.Palmer complete to 15-M.Floyd. 15-M.Floyd runs 10 yards for a touchdown.]]></summary>
          <links>
            <link href="/2013/REG/6/ARI/SF/plays/be01222a-f1c7-4ca3-a8d9-eae1fa8354d2.xml" rel="summary" type="application/xml"/>
          </links>
        </score>
      </drive>
      <drive clock="01:07" quarter="3" sequence="9" team="SF">
        <score clock="06:40" points="6" quarter="4" type="touchdown">
          <summary><![CDATA[32-K.Hunter runs 6 yards for a touchdown.]]></summary>
          <links>
            <link href="/2013/REG/6/ARI/SF/plays/5ae11041-28c5-4e75-94ee-8b4f5167ac12.xml" rel="summary" type="application/xml"/>
          </links>
        </score>
        <score clock="06:35" points="1" quarter="4" type="extrapoint">
          <summary><![CDATA[9-P.Dawson extra point is good.]]></summary>
          <links>
            <link href="/2013/REG/6/ARI/SF/plays/88c49b74-8ea8-4ca0-b62e-c885443d638d.xml" rel="summary" type="application/xml"/>
          </links>
        </score>
      </drive>
      <drive clock="05:56" quarter="4" sequence="10" team="SF">
        <score clock="04:20" points="3" quarter="4" type="fieldgoal">
          <summary><![CDATA[9-P.Dawson 44 yards Field Goal is Good.]]></summary>
          <links>
            <link href="/2013/REG/6/ARI/SF/plays/90ef7c2d-22b0-4a9b-ad8a-6788926e2ce1.xml" rel="summary" type="application/xml"/>
          </links>
        </score>
      </drive>
    </scoring_drives>
  </game>
  <game away="PHI" clock=":00" completed="2013-10-13T20:06:18+00:00" home="TB" id="8e142368-c61b-43f7-9597-0692b0fd7e92" quarter="4" scheduled="2013-10-13T17:00:00+00:00" status="closed">
    <team id="TB" market="Tampa Bay" name="Buccaneers" remaining_challenges="2" remaining_timeouts="2">
      <scoring points="20">
        <quarter number="1" points="3"/>
        <quarter number="2" points="14"/>
        <quarter number="3" points="0"/>
        <quarter number="4" points="3"/>
      </scoring>
    </team>
    <team id="PHI" market="Philadelphia" name="Eagles" remaining_challenges="2" remaining_timeouts="2">
      <scoring points="31">
        <quarter number="1" points="7"/>
        <quarter number="2" points="7"/>
        <quarter number="3" points="7"/>
        <quarter number="4" points="10"/>
      </scoring>
    </team>
    <scoring_drives>
      <drive clock="15:00" quarter="1" sequence="1" team="PHI">
        <score clock="11:51" points="6" quarter="1" type="touchdown">
          <summary><![CDATA[9-N.Foles runs 4 yards for a touchdown.]]></summary>
          <links>
            <link href="/2013/REG/6/PHI/TB/plays/e0a2fe46-424c-4b49-bc70-d001dfd25027.xml" rel="summary" type="application/xml"/>
          </links>
        </score>
        <score clock="11:46" points="1" quarter="1" type="extrapoint">
          <summary><![CDATA[6-A.Henery extra point is good.]]></summary>
          <links>
            <link href="/2013/REG/6/PHI/TB/plays/b4d5ed94-8d90-4d44-90ec-5a78b3ae44b9.xml" rel="summary" type="application/xml"/>
          </links>
        </score>
      </drive>
      <drive clock="10:36" quarter="1" sequence="2" team="TB">
        <score clock="06:36" points="3" quarter="1" type="fieldgoal">
          <summary><![CDATA[4-R.Lindell 38 yards Field Goal is Good.]]></summary>
          <links>
            <link href="/2013/REG/6/PHI/TB/plays/a305e5a6-8b46-4928-8b92-9762cfa96617.xml" rel="summary" type="application/xml"/>
          </links>
        </score>
      </drive>
      <drive clock=":41" quarter="1" sequence="3" team="TB">
        <score clock="14:54" points="6" quarter="2" type="touchdown">
          <summary><![CDATA[8-M.Glennon complete to 83-V.Jackson. 83-V.Jackson runs 24 yards for a touchdown.]]></summary>
          <links>
            <link href="/2013/REG/6/PHI/TB/plays/5e2fcc40-1096-4c5b-9ae3-42c2bca27627.xml" rel="summary" type="application/xml"/>
          </links>
        </score>
        <score clock="14:46" points="1" quarter="2" type="extrapoint">
          <summary><![CDATA[4-R.Lindell extra point is good.]]></summary>
          <links>
            <link href="/2013/REG/6/PHI/TB/plays/7da9f883-e5d0-453c-bbc5-ca4dc4635233.xml" rel="summary" type="application/xml"/>
          </links>
        </score>
      </drive>
      <drive clock="10:25" quarter="2" sequence="4" team="PHI">
        <score clock="07:13" points="6" quarter="2" type="touchdown">
          <summary><![CDATA[9-N.Foles complete to 10-D.Jackson. 10-D.Jackson runs 12 yards for a touchdown.]]></summary>
          <links>
            <link href="/2013/REG/6/PHI/TB/plays/397ff116-c96d-47f0-a248-0355b6f565fc.xml" rel="summary" type="application/xml"/>
          </links>
        </score>
        <score clock="07:05" points="1" quarter="2" type="extrapoint">
          <summary><![CDATA[6-A.Henery extra point is good.]]></summary>
          <links>
            <link href="/2013/REG/6/PHI/TB/plays/2d6875f7-9427-461d-9a9b-8726a4acfee7.xml" rel="summary" type="application/xml"/>
          </links>
        </score>
      </drive>
      <drive clock="07:05" quarter="2" sequence="5" team="TB">
        <score clock="01:08" points="6" quarter="2" type="touchdown">
          <summary><![CDATA[8-M.Glennon complete to 83-V.Jackson. 83-V.Jackson runs 1 yard for a touchdown.]]></summary>
          <links>
            <link href="/2013/REG/6/PHI/TB/plays/05635a94-0466-452e-89fb-45f708371a42.xml" rel="summary" type="application/xml"/>
          </links>
        </score>
        <score clock="01:02" points="1" quarter="2" type="extrapoint">
          <summary><![CDATA[4-R.Lindell extra point is good.]]></summary>
          <links>
            <link href="/2013/REG/6/PHI/TB/plays/9b848702-44af-478e-997d-c332b44ff6de.xml" rel="summary" type="application/xml"/>
          </links>
        </score>
      </drive>
      <drive clock="13:39" quarter="3" sequence="6" team="PHI">
        <score clock="11:51" points="6" quarter="3" type="touchdown">
          <summary><![CDATA[9-N.Foles complete to 14-R.Cooper. 14-R.Cooper runs 47 yards for a touchdown.]]></summary>
          <links>
            <link href="/2013/REG/6/PHI/TB/plays/56684dce-4208-431e-a40b-658a6c7a74b1.xml" rel="summary" type="application/xml"/>
          </links>
        </score>
        <score clock="11:41" points="1" quarter="3" type="extrapoint">
          <summary><![CDATA[6-A.Henery extra point is good.]]></summary>
          <links>
            <link href="/2013/REG/6/PHI/TB/plays/1f0d8487-c971-4d3b-b6f5-6621814e6f3b.xml" rel="summary" type="application/xml"/>
          </links>
        </score>
      </drive>
      <drive clock="03:45" quarter="3" sequence="7" team="TB">
        <score clock="10:52" points="3" quarter="4" type="fieldgoal">
          <summary><![CDATA[4-R.Lindell 27 yards Field Goal is Good.]]></summary>
          <links>
            <link href="/2013/REG/6/PHI/TB/plays/90a84b54-df6e-4b40-98bd-c65a31ce56ea.xml" rel="summary" type="application/xml"/>
          </links>
        </score>
      </drive>
      <drive clock="10:48" quarter="4" sequence="8" team="PHI">
        <score clock="09:41" points="6" quarter="4" type="touchdown">
          <summary><![CDATA[9-N.Foles complete to 10-D.Jackson. 10-D.Jackson runs 36 yards for a touchdown.]]></summary>
          <links>
            <link href="/2013/REG/6/PHI/TB/plays/b61d772a-d66f-4abf-bf81-32f0d147276e.xml" rel="summary" type="application/xml"/>
          </links>
        </score>
        <score clock="09:32" points="1" quarter="4" type="extrapoint">
          <summary><![CDATA[6-A.Henery extra point is good.]]></summary>
          <links>
            <link href="/2013/REG/6/PHI/TB/plays/33d738e3-3ae1-4cef-8a1b-4c2e3a2e5f15.xml" rel="summary" type="application/xml"/>
          </links>
        </score>
      </drive>
      <drive clock="08:03" quarter="4" sequence="9" team="PHI">
        <score clock="02:38" points="3" quarter="4" type="fieldgoal">
          <summary><![CDATA[6-A.Henery 24 yards Field Goal is Good.]]></summary>
          <links>
            <link href="/2013/REG/6/PHI/TB/plays/78fd89af-088b-4f1a-9262-90130e8f9bce.xml" rel="summary" type="application/xml"/>
          </links>
        </score>
      </drive>
    </scoring_drives>
  </game>
  <game away="CAR" clock=":00" completed="2013-10-13T19:59:55+00:00" home="MIN" id="d11d883a-c9ae-497c-b5d6-50d2f81af1e7" quarter="4" scheduled="2013-10-13T17:00:00+00:00" status="closed">
    <team id="MIN" market="Minnesota" name="Vikings" remaining_challenges="2" remaining_timeouts="2">
      <scoring points="10">
        <quarter number="1" points="0"/>
        <quarter number="2" points="3"/>
        <quarter number="3" points="0"/>
        <quarter number="4" points="7"/>
      </scoring>
    </team>
    <team id="CAR" market="Carolina" name="Panthers" remaining_challenges="2" remaining_timeouts="2">
      <scoring points="35">
        <quarter number="1" points="7"/>
        <quarter number="2" points="7"/>
        <quarter number="3" points="14"/>
        <quarter number="4" points="7"/>
      </scoring>
    </team>
    <scoring_drives>
      <drive clock="11:32" quarter="1" sequence="1" team="CAR">
        <score clock="02:07" points="6" quarter="1" type="touchdown">
          <summary><![CDATA[1-C.Newton complete to 89-S.Smith. 89-S.Smith runs 2 yards for a touchdown.]]></summary>
          <links>
            <link href="/2013/REG/6/CAR/MIN/plays/3e9a1186-2a35-4043-adcd-ae05e5da9e43.xml" rel="summary" type="application/xml"/>
          </links>
        </score>
        <score clock="02:03" points="1" quarter="1" type="extrapoint">
          <summary><![CDATA[9-G.Gano extra point is good.]]></summary>
          <links>
            <link href="/2013/REG/6/CAR/MIN/plays/f05f466b-09fc-4fd4-bb14-cb802c86c222.xml" rel="summary" type="application/xml"/>
          </links>
        </score>
      </drive>
      <drive clock="10:17" quarter="2" sequence="2" team="CAR">
        <score clock="03:52" points="6" quarter="2" type="touchdown">
          <summary><![CDATA[1-C.Newton complete to 35-M.Tolbert. 35-M.Tolbert runs 10 yards for a touchdown.]]></summary>
          <links>
            <link href="/2013/REG/6/CAR/MIN/plays/dee73bc3-192c-484f-b747-e2462bc562ee.xml" rel="summary" type="application/xml"/>
          </links>
        </score>
        <score clock="03:43" points="1" quarter="2" type="extrapoint">
          <summary><![CDATA[9-G.Gano extra point is good.]]></summary>
          <links>
            <link href="/2013/REG/6/CAR/MIN/plays/3f8f2c0b-912f-4b5e-a75c-054cd78819e6.xml" rel="summary" type="application/xml"/>
          </links>
        </score>
      </drive>
      <drive clock="03:43" quarter="2" sequence="3" team="MIN">
        <score clock=":17" points="3" quarter="2" type="fieldgoal">
          <summary><![CDATA[3-B.Walsh 22 yards Field Goal is Good.]]></summary>
          <links>
            <link href="/2013/REG/6/CAR/MIN/plays/d9ed928f-de31-43d7-b0f2-83dd4a400e79.xml" rel="summary" type="application/xml"/>
          </links>
        </score>
      </drive>
      <drive clock="15:00" quarter="3" sequence="4" team="CAR">
        <score clock="14:08" points="6" quarter="3" type="touchdown">
          <summary><![CDATA[1-C.Newton complete to 11-B.LaFell. 11-B.LaFell runs 79 yards for a touchdown.]]></summary>
          <links>
            <link href="/2013/REG/6/CAR/MIN/plays/73136ab6-aedb-4292-b97f-ae23b32f4128.xml" rel="summary" type="application/xml"/>
          </links>
        </score>
        <score clock="13:56" points="1" quarter="3" type="extrapoint">
          <summary><![CDATA[9-G.Gano extra point is good.]]></summary>
          <links>
            <link href="/2013/REG/6/CAR/MIN/plays/99137792-300c-4117-9103-a480ad9552e8.xml" rel="summary" type="application/xml"/>
          </links>
        </score>
      </drive>
      <drive clock="12:00" quarter="3" sequence="5" team="CAR">
        <score clock="06:20" points="6" quarter="3" type="touchdown">
          <summary><![CDATA[1-C.Newton runs 7 yards for a touchdown.]]></summary>
          <links>
            <link href="/2013/REG/6/CAR/MIN/plays/d5f33be4-bb76-4aa9-a762-279d3f21dcdb.xml" rel="summary" type="application/xml"/>
          </links>
        </score>
        <score clock="06:10" points="1" quarter="3" type="extrapoint">
          <summary><![CDATA[9-G.Gano extra point is good.]]></summary>
          <links>
            <link href="/2013/REG/6/CAR/MIN/plays/34f49648-8263-4613-8176-3daa7d575385.xml" rel="summary" type="application/xml"/>
          </links>
        </score>
      </drive>
      <drive clock="10:42" quarter="4" sequence="6" team="CAR">
        <score clock="07:41" points="6" quarter="4" type="touchdown">
          <summary><![CDATA[35-M.Tolbert runs 1 yard for a touchdown.]]></summary>
          <links>
            <link href="/2013/REG/6/CAR/MIN/plays/2fa8f86a-4cc9-42c1-8e1a-cc37aa2b7674.xml" rel="summary" type="application/xml"/>
          </links>
        </score>
        <score clock="07:40" points="1" quarter="4" type="extrapoint">
          <summary><![CDATA[9-G.Gano extra point is good.]]></summary>
          <links>
            <link href="/2013/REG/6/CAR/MIN/plays/b69e9600-06c1-436b-a890-eb4ee2b011d8.xml" rel="summary" type="application/xml"/>
          </links>
        </score>
      </drive>
      <drive clock="03:38" quarter="4" sequence="7" team="MIN">
        <score clock="01:07" points="6" quarter="4" type="touchdown">
          <summary><![CDATA[16-M.Cassel complete to 82-K.Rudolph. 82-K.Rudolph runs 23 yards for a touchdown.]]></summary>
          <links>
            <link href="/2013/REG/6/CAR/MIN/plays/ed9866e4-1d85-4cf5-aba3-3849be5c214a.xml" rel="summary" type="application/xml"/>
          </links>
        </score>
        <score clock="01:00" points="1" quarter="4" type="extrapoint">
          <summary><![CDATA[3-B.Walsh extra point is good.]]></summary>
          <links>
            <link href="/2013/REG/6/CAR/MIN/plays/36164853-ee33-4539-9e5f-2162bc347c50.xml" rel="summary" type="application/xml"/>
          </links>
        </score>
      </drive>
    </scoring_drives>
  </game>
  <game away="WAS" clock=":00" completed="2013-10-14T03:39:45+00:00" home="DAL" id="d099476b-b195-4d05-ac5e-38d87d48dacc" quarter="4" scheduled="2013-10-14T00:30:00+00:00" status="closed">
    <team id="DAL" market="Dallas" name="Cowboys" remaining_challenges="2" remaining_timeouts="2">
      <scoring points="31">
        <quarter number="1" points="7"/>
        <quarter number="2" points="7"/>
        <quarter number="3" points="7"/>
        <quarter number="4" points="10"/>
      </scoring>
    </team>
    <team id="WAS" market="Washington" name="Redskins" remaining_challenges="2" remaining_timeouts="2">
      <scoring points="16">
        <quarter number="1" points="3"/>
        <quarter number="2" points="3"/>
        <quarter number="3" points="10"/>
        <quarter number="4" points="0"/>
      </scoring>
    </team>
    <scoring_drives>
      <drive clock="15:00" quarter="1" sequence="1" team="DAL">
        <score clock="08:57" points="6" quarter="1" type="touchdown">
          <summary><![CDATA[29-D.Murray runs 4 yards for a touchdown.]]></summary>
          <links>
            <link href="/2013/REG/6/WAS/DAL/plays/106fee1d-26a6-4806-93d6-3f72f661d78b.xml" rel="summary" type="application/xml"/>
          </links>
        </score>
        <score clock="08:52" points="1" quarter="1" type="extrapoint">
          <summary><![CDATA[5-D.Bailey extra point is good.]]></summary>
          <links>
            <link href="/2013/REG/6/WAS/DAL/plays/760015a6-ba1c-4456-a557-199236fa185d.xml" rel="summary" type="application/xml"/>
          </links>
        </score>
      </drive>
      <drive clock="08:52" quarter="1" sequence="2" team="WAS">
        <score clock="01:43" points="3" quarter="1" type="fieldgoal">
          <summary><![CDATA[2-K.Forbath 20 yards Field Goal is Good.]]></summary>
          <links>
            <link href="/2013/REG/6/WAS/DAL/plays/ab59d31c-b06b-427c-91cb-c1d2215b97dc.xml" rel="summary" type="application/xml"/>
          </links>
        </score>
      </drive>
      <drive clock="06:03" quarter="2" sequence="3" team="WAS">
        <score clock="02:45" points="6" quarter="2" type="touchdown">
          <summary><![CDATA[6-S.Rocca punts 51 yards from WAS 35. 17-D.Harris runs 86 yards for a touchdown.]]></summary>
          <links>
            <link href="/2013/REG/6/WAS/DAL/plays/e7bdd5c9-4ebf-41d9-b438-8f40053b03f7.xml" rel="summary" type="application/xml"/>
          </links>
        </score>
      </drive>
      <drive clock="02:26" quarter="2" sequence="4" team="DAL">
        <score clock="02:26" points="1" quarter="2" type="extrapoint">
          <summary><![CDATA[5-D.Bailey extra point is good.]]></summary>
          <links>
            <link href="/2013/REG/6/WAS/DAL/plays/080d563f-6802-45a5-8f8c-661e38da1bd7.xml" rel="summary" type="application/xml"/>
          </links>
        </score>
      </drive>
      <drive clock="02:26" quarter="2" sequence="5" team="WAS">
        <score clock=":01" points="3" quarter="2" type="fieldgoal">
          <summary><![CDATA[2-K.Forbath 32 yards Field Goal is Good.]]></summary>
          <links>
            <link href="/2013/REG/6/WAS/DAL/plays/e27956be-5804-48bc-bac3-99be1fbe146c.xml" rel="summary" type="application/xml"/>
          </links>
        </score>
      </drive>
      <drive clock="15:00" quarter="3" sequence="6" team="WAS">
        <score clock="10:08" points="3" quarter="3" type="fieldgoal">
          <summary><![CDATA[2-K.Forbath 33 yards Field Goal is Good.]]></summary>
          <links>
            <link href="/2013/REG/6/WAS/DAL/plays/b6ae4a8e-9051-48e3-a012-b21c05dffbf5.xml" rel="summary" type="application/xml"/>
          </links>
        </score>
      </drive>
      <drive clock="10:03" quarter="3" sequence="7" team="DAL">
        <score clock="09:11" points="6" quarter="3" type="touchdown">
          <summary><![CDATA[9-T.Romo complete to 83-T.Williams. 83-T.Williams runs 15 yards for a touchdown.]]></summary>
          <links>
            <link href="/2013/REG/6/WAS/DAL/plays/6d3e5b55-7e42-4a3d-8971-7274af142b1b.xml" rel="summary" type="application/xml"/>
          </links>
        </score>
        <score clock="09:03" points="1" quarter="3" type="extrapoint">
          <summary><![CDATA[5-D.Bailey extra point is good.]]></summary>
          <links>
            <link href="/2013/REG/6/WAS/DAL/plays/1be454b5-de3b-4436-a8d2-01783ec7b383.xml" rel="summary" type="application/xml"/>
          </links>
        </score>
      </drive>
      <drive clock="04:20" quarter="3" sequence="8" team="WAS">
        <score clock="03:50" points="6" quarter="3" type="touchdown">
          <summary><![CDATA[46-A.Morris runs 45 yards for a touchdown. Penalty on DAL 95-C.Rayford, Offside, declined.]]></summary>
          <links>
            <link href="/2013/REG/6/WAS/DAL/plays/689da1dc-4e14-4b95-b289-387b358f6209.xml" rel="summary" type="application/xml"/>
          </links>
        </score>
        <score clock="03:43" points="1" quarter="3" type="extrapoint">
          <summary><![CDATA[2-K.Forbath extra point is good.]]></summary>
          <links>
            <link href="/2013/REG/6/WAS/DAL/plays/d826df66-ecc8-4cb8-80cb-b4b2011977f7.xml" rel="summary" type="application/xml"/>
          </links>
        </score>
      </drive>
      <drive clock="14:42" quarter="4" sequence="9" team="DAL">
        <score clock="10:40" points="3" quarter="4" type="fieldgoal">
          <summary><![CDATA[5-D.Bailey 30 yards Field Goal is Good.]]></summary>
          <links>
            <link href="/2013/REG/6/WAS/DAL/plays/58abaec8-0579-485e-ad8c-b241379f9649.xml" rel="summary" type="application/xml"/>
          </links>
        </score>
      </drive>
      <drive clock="09:36" quarter="4" sequence="10" team="DAL">
        <score clock="08:56" points="6" quarter="4" type="touchdown">
          <summary><![CDATA[21-J.Randle runs 1 yard for a touchdown.]]></summary>
          <links>
            <link href="/2013/REG/6/WAS/DAL/plays/2c719b92-9b6c-45ca-9ce6-1573d14af652.xml" rel="summary" type="application/xml"/>
          </links>
        </score>
        <score clock="08:49" points="1" quarter="4" type="extrapoint">
          <summary><![CDATA[5-D.Bailey extra point is good.]]></summary>
          <links>
            <link href="/2013/REG/6/WAS/DAL/plays/8fd145f7-8fd2-496e-a968-372aaa595ca0.xml" rel="summary" type="application/xml"/>
          </links>
        </score>
      </drive>
    </scoring_drives>
  </game>
  <game away="IND" clock=":00" completed="2013-10-15T03:39:05+00:00" home="SD" id="45787908-3a63-4981-a1cd-d3f535dbd969" quarter="4" scheduled="2013-10-15T00:40:00+00:00" status="closed">
    <team id="SD" market="San Diego" name="Chargers" remaining_challenges="1" remaining_timeouts="2">
      <scoring points="19">
        <quarter number="1" points="0"/>
        <quarter number="2" points="10"/>
        <quarter number="3" points="3"/>
        <quarter number="4" points="6"/>
      </scoring>
    </team>
    <team id="IND" market="Indianapolis" name="Colts" remaining_challenges="2" remaining_timeouts="2">
      <scoring points="9">
        <quarter number="1" points="3"/>
        <quarter number="2" points="3"/>
        <quarter number="3" points="0"/>
        <quarter number="4" points="3"/>
      </scoring>
    </team>
    <scoring_drives>
      <drive clock="15:00" quarter="1" sequence="1" team="IND">
        <score clock="11:30" points="3" quarter="1" type="fieldgoal">
          <summary><![CDATA[4-A.Vinatieri 30 yards Field Goal is Good.]]></summary>
          <links>
            <link href="/2013/REG/6/IND/SD/plays/6270ae26-435c-4acf-94f6-2df7267060e4.xml" rel="summary" type="application/xml"/>
          </links>
        </score>
      </drive>
      <drive clock="03:16" quarter="1" sequence="2" team="SD">
        <score clock="12:10" points="6" quarter="2" type="touchdown">
          <summary><![CDATA[17-P.Rivers complete to 13-K.Allen. 13-K.Allen runs 22 yards for a touchdown.]]></summary>
          <links>
            <link href="/2013/REG/6/IND/SD/plays/60c43133-a016-499a-82e7-1b71fff9b972.xml" rel="summary" type="application/xml"/>
          </links>
        </score>
        <score clock="12:02" points="1" quarter="2" type="extrapoint">
          <summary><![CDATA[9-N.Novak extra point is good.]]></summary>
          <links>
            <link href="/2013/REG/6/IND/SD/plays/d9c1a632-7e30-4d77-ae05-8cd791fb65d9.xml" rel="summary" type="application/xml"/>
          </links>
        </score>
      </drive>
      <drive clock="09:39" quarter="2" sequence="3" team="SD">
        <score clock="01:45" points="3" quarter="2" type="fieldgoal">
          <summary><![CDATA[9-N.Novak 31 yards Field Goal is Good.]]></summary>
          <links>
            <link href="/2013/REG/6/IND/SD/plays/d5cec747-0060-4292-9913-6abe3af95c21.xml" rel="summary" type="application/xml"/>
          </links>
        </score>
      </drive>
      <drive clock="01:41" quarter="2" sequence="4" team="IND">
        <score clock=":05" points="3" quarter="2" type="fieldgoal">
          <summary><![CDATA[4-A.Vinatieri 50 yards Field Goal is Good.]]></summary>
          <links>
            <link href="/2013/REG/6/IND/SD/plays/1d1d5a30-85c0-4618-b68c-c58b6e83e96c.xml" rel="summary" type="application/xml"/>
          </links>
        </score>
      </drive>
      <drive clock="15:00" quarter="3" sequence="5" team="SD">
        <score clock="09:09" points="3" quarter="3" type="fieldgoal">
          <summary><![CDATA[9-N.Novak 33 yards Field Goal is Good.]]></summary>
          <links>
            <link href="/2013/REG/6/IND/SD/plays/39ec6f32-43a0-487c-9767-40baecff51c0.xml" rel="summary" type="application/xml"/>
          </links>
        </score>
      </drive>
      <drive clock="03:56" quarter="3" sequence="6" team="SD">
        <score clock="09:46" points="3" quarter="4" type="fieldgoal">
          <summary><![CDATA[9-N.Novak 34 yards Field Goal is Good.]]></summary>
          <links>
            <link href="/2013/REG/6/IND/SD/plays/58b3c029-046b-4f63-bf93-96e249a02f78.xml" rel="summary" type="application/xml"/>
          </links>
        </score>
      </drive>
      <drive clock="09:43" quarter="4" sequence="7" team="IND">
        <score clock="07:26" points="3" quarter="4" type="fieldgoal">
          <summary><![CDATA[4-A.Vinatieri 51 yards Field Goal is Good.]]></summary>
          <links>
            <link href="/2013/REG/6/IND/SD/plays/c9d1b20d-724c-4b2e-a1c3-9d6f49d9752f.xml" rel="summary" type="application/xml"/>
          </links>
        </score>
      </drive>
      <drive clock="03:17" quarter="4" sequence="8" team="SD">
        <score clock="02:00" points="3" quarter="4" type="fieldgoal">
          <summary><![CDATA[9-N.Novak 50 yards Field Goal is Good.]]></summary>
          <links>
            <link href="/2013/REG/6/IND/SD/plays/adef5a1a-c517-49a9-b3fa-dffb1a2b4225.xml" rel="summary" type="application/xml"/>
          </links>
        </score>
      </drive>
    </scoring_drives>
  </game>
  <game away="PIT" clock=":00" completed="2013-10-13T20:03:13+00:00" home="NYJ" id="53c476f5-543f-46e4-952a-39078ed54535" quarter="4" scheduled="2013-10-13T17:00:00+00:00" status="closed">
    <team id="NYJ" market="New York" name="Jets" remaining_challenges="2" remaining_timeouts="2">
      <scoring points="6">
        <quarter number="1" points="3"/>
        <quarter number="2" points="3"/>
        <quarter number="3" points="0"/>
        <quarter number="4" points="0"/>
      </scoring>
    </team>
    <team id="PIT" market="Pittsburgh" name="Steelers" remaining_challenges="2" remaining_timeouts="2">
      <scoring points="19">
        <quarter number="1" points="0"/>
        <quarter number="2" points="9"/>
        <quarter number="3" points="7"/>
        <quarter number="4" points="3"/>
      </scoring>
    </team>
    <scoring_drives>
      <drive clock="09:04" quarter="1" sequence="1" team="NYJ">
        <score clock="03:29" points="3" quarter="1" type="fieldgoal">
          <summary><![CDATA[2-N.Folk 25 yards Field Goal is Good.]]></summary>
          <links>
            <link href="/2013/REG/6/PIT/NYJ/plays/fb236161-ba43-4263-acd8-e79c1f511d7e.xml" rel="summary" type="application/xml"/>
          </links>
        </score>
      </drive>
      <drive clock="03:25" quarter="1" sequence="2" team="PIT">
        <score clock="12:12" points="3" quarter="2" type="fieldgoal">
          <summary><![CDATA[6-S.Suisham 46 yards Field Goal is Good.]]></summary>
          <links>
            <link href="/2013/REG/6/PIT/NYJ/plays/0e50e83c-6436-4afb-bf8d-18f91c5bc8b4.xml" rel="summary" type="application/xml"/>
          </links>
        </score>
      </drive>
      <drive clock="10:08" quarter="2" sequence="3" team="PIT">
        <score clock="05:28" points="3" quarter="2" type="fieldgoal">
          <summary><![CDATA[6-S.Suisham 33 yards Field Goal is Good.]]></summary>
          <links>
            <link href="/2013/REG/6/PIT/NYJ/plays/73fbc52c-c2b2-409c-baf1-d30c53029c28.xml" rel="summary" type="application/xml"/>
          </links>
        </score>
      </drive>
      <drive clock="04:03" quarter="2" sequence="4" team="PIT">
        <score clock=":49" points="3" quarter="2" type="fieldgoal">
          <summary><![CDATA[6-S.Suisham 48 yards Field Goal is Good.]]></summary>
          <links>
            <link href="/2013/REG/6/PIT/NYJ/plays/74f878cb-f0b6-41fb-b4b6-6adbbe520f42.xml" rel="summary" type="application/xml"/>
          </links>
        </score>
      </drive>
      <drive clock=":45" quarter="2" sequence="5" team="NYJ">
        <score clock=":05" points="3" quarter="2" type="fieldgoal">
          <summary><![CDATA[2-N.Folk 39 yards Field Goal is Good.]]></summary>
          <links>
            <link href="/2013/REG/6/PIT/NYJ/plays/af64f601-3792-4960-b0c1-d30291d2e60c.xml" rel="summary" type="application/xml"/>
          </links>
        </score>
      </drive>
      <drive clock="14:01" quarter="3" sequence="6" team="PIT">
        <score clock="12:39" points="6" quarter="3" type="touchdown">
          <summary><![CDATA[7-B.Roethlisberger complete to 88-E.Sanders. 88-E.Sanders runs 55 yards for a touchdown.]]></summary>
          <links>
            <link href="/2013/REG/6/PIT/NYJ/plays/a0a48b5d-c810-4b74-8a06-d3b75715af1b.xml" rel="summary" type="application/xml"/>
          </links>
        </score>
        <score clock="12:30" points="1" quarter="3" type="extrapoint">
          <summary><![CDATA[6-S.Suisham extra point is good.]]></summary>
          <links>
            <link href="/2013/REG/6/PIT/NYJ/plays/ff75ccbc-433e-4b40-864b-28f14dda1eae.xml" rel="summary" type="application/xml"/>
          </links>
        </score>
      </drive>
      <drive clock="04:11" quarter="3" sequence="7" team="PIT">
        <score clock="12:12" points="3" quarter="4" type="fieldgoal">
          <summary><![CDATA[6-S.Suisham 32 yards Field Goal is Good.]]></summary>
          <links>
            <link href="/2013/REG/6/PIT/NYJ/plays/a052988c-732c-45db-a309-32ef0fee567d.xml" rel="summary" type="application/xml"/>
          </links>
        </score>
      </drive>
    </scoring_drives>
  </game>
  <game away="NYG" clock=":00" completed="2013-10-11T03:21:23+00:00" home="CHI" id="ce60383a-6b41-464f-a02d-6f2b43678cae" quarter="4" scheduled="2013-10-11T00:25:00+00:00" status="closed">
    <team id="CHI" market="Chicago" name="Bears" remaining_challenges="2" remaining_timeouts="2">
      <scoring points="27">
        <quarter number="1" points="7"/>
        <quarter number="2" points="17"/>
        <quarter number="3" points="3"/>
        <quarter number="4" points="0"/>
      </scoring>
    </team>
    <team id="NYG" market="New York" name="Giants" remaining_challenges="2" remaining_timeouts="2">
      <scoring points="21">
        <quarter number="1" points="7"/>
        <quarter number="2" points="7"/>
        <quarter number="3" points="7"/>
        <quarter number="4" points="0"/>
      </scoring>
    </team>
    <scoring_drives>
      <drive clock="12:03" quarter="1" sequence="1" team="NYG">
        <score clock="10:02" points="6" quarter="1" type="touchdown">
          <summary><![CDATA[10-E.Manning incomplete. Intended for 82-R.Randle, INTERCEPTED by 26-T.Jennings at NYG 48. 26-T.Jennings runs 48 yards for a touchdown.]]></summary>
          <links>
            <link href="/2013/REG/6/NYG/CHI/plays/909cf25c-9a14-42a9-8480-a567b87c5ce5.xml" rel="summary" type="application/xml"/>
          </links>
        </score>
      </drive>
      <drive clock="09:50" quarter="1" sequence="2" team="CHI">
        <score clock="09:50" points="1" quarter="1" type="extrapoint">
          <summary><![CDATA[9-R.Gould extra point is good.]]></summary>
          <links>
            <link href="/2013/REG/6/NYG/CHI/plays/782d131a-d186-4483-a85c-a39a1a53f057.xml" rel="summary" type="application/xml"/>
          </links>
        </score>
      </drive>
      <drive clock="09:50" quarter="1" sequence="3" team="NYG">
        <score clock="03:55" points="6" quarter="1" type="touchdown">
          <summary><![CDATA[34-B.Jacobs runs 4 yards for a touchdown.]]></summary>
          <links>
            <link href="/2013/REG/6/NYG/CHI/plays/ec9015c6-38c9-4e6f-aad2-acc4dcd505a6.xml" rel="summary" type="application/xml"/>
          </links>
        </score>
        <score clock="03:48" points="1" quarter="1" type="extrapoint">
          <summary><![CDATA[3-J.Brown extra point is good.]]></summary>
          <links>
            <link href="/2013/REG/6/NYG/CHI/plays/bf8c8530-d56e-4148-8a96-2180fafee3b9.xml" rel="summary" type="application/xml"/>
          </links>
        </score>
      </drive>
      <drive clock="03:48" quarter="1" sequence="4" team="CHI">
        <score clock="14:23" points="6" quarter="2" type="touchdown">
          <summary><![CDATA[6-J.Cutler complete to 15-B.Marshall. 15-B.Marshall runs 10 yards for a touchdown.]]></summary>
          <links>
            <link href="/2013/REG/6/NYG/CHI/plays/af4410b1-3fab-4ab3-b14a-c3552c7721ba.xml" rel="summary" type="application/xml"/>
          </links>
        </score>
        <score clock="14:18" points="1" quarter="2" type="extrapoint">
          <summary><![CDATA[9-R.Gould extra point is good.]]></summary>
          <links>
            <link href="/2013/REG/6/NYG/CHI/plays/481a9c02-e155-491b-81a7-d9f5c9973e6d.xml" rel="summary" type="application/xml"/>
          </links>
        </score>
      </drive>
      <drive clock="14:18" quarter="2" sequence="5" team="NYG">
        <score clock="10:41" points="6" quarter="2" type="touchdown">
          <summary><![CDATA[10-E.Manning complete to 82-R.Randle. 82-R.Randle runs 37 yards for a touchdown.]]></summary>
          <links>
            <link href="/2013/REG/6/NYG/CHI/plays/6e9330f7-a33d-41e9-948d-20281a668fb9.xml" rel="summary" type="application/xml"/>
          </links>
        </score>
        <score clock="10:31" points="1" quarter="2" type="extrapoint">
          <summary><![CDATA[3-J.Brown extra point is good.]]></summary>
          <links>
            <link href="/2013/REG/6/NYG/CHI/plays/7cb4fde5-6809-42d7-bed8-b0cf2b3b0f92.xml" rel="summary" type="application/xml"/>
          </links>
        </score>
      </drive>
      <drive clock="10:31" quarter="2" sequence="6" team="CHI">
        <score clock="05:24" points="6" quarter="2" type="touchdown">
          <summary><![CDATA[6-J.Cutler complete to 15-B.Marshall. 15-B.Marshall runs 3 yards for a touchdown.]]></summary>
          <links>
            <link href="/2013/REG/6/NYG/CHI/plays/d43b0ccd-540c-4de9-b0ba-19e038dbf008.xml" rel="summary" type="application/xml"/>
          </links>
        </score>
        <score clock="05:20" points="1" quarter="2" type="extrapoint">
          <summary><![CDATA[9-R.Gould extra point is good.]]></summary>
          <links>
            <link href="/2013/REG/6/NYG/CHI/plays/c4563266-8050-46a5-ae65-59f2426f1a8a.xml" rel="summary" type="application/xml"/>
          </links>
        </score>
      </drive>
      <drive clock="03:34" quarter="2" sequence="7" team="CHI">
        <score clock=":06" points="3" quarter="2" type="fieldgoal">
          <summary><![CDATA[9-R.Gould 40 yards Field Goal is Good.]]></summary>
          <links>
            <link href="/2013/REG/6/NYG/CHI/plays/2b03f3d4-cb59-48f7-89bb-4d16cba1867a.xml" rel="summary" type="application/xml"/>
          </links>
        </score>
      </drive>
      <drive clock="15:00" quarter="3" sequence="8" team="CHI">
        <score clock="11:29" points="3" quarter="3" type="fieldgoal">
          <summary><![CDATA[9-R.Gould 52 yards Field Goal is Good.]]></summary>
          <links>
            <link href="/2013/REG/6/NYG/CHI/plays/055ecb62-6c86-4688-9ab3-8f4d131b1983.xml" rel="summary" type="application/xml"/>
          </links>
        </score>
      </drive>
      <drive clock="05:21" quarter="3" sequence="9" team="NYG">
        <score clock=":10" points="6" quarter="3" type="touchdown">
          <summary><![CDATA[34-B.Jacobs runs 1 yard for a touchdown.]]></summary>
          <links>
            <link href="/2013/REG/6/NYG/CHI/plays/c2cd98f2-b848-4d01-90a1-880063f6e1af.xml" rel="summary" type="application/xml"/>
          </links>
        </score>
        <score clock=":06" points="1" quarter="3" type="extrapoint">
          <summary><![CDATA[3-J.Brown extra point is good.]]></summary>
          <links>
            <link href="/2013/REG/6/NYG/CHI/plays/da33610c-7b37-4c6f-8f5b-9cde07fc473c.xml" rel="summary" type="application/xml"/>
          </links>
        </score>
      </drive>
    </scoring_drives>
  </game>
  <game away="DET" clock=":00" completed="2013-10-13T20:17:28+00:00" home="CLE" id="464307fb-5e6b-4048-9660-968ddd7c79a3" quarter="4" scheduled="2013-10-13T17:00:00+00:00" status="closed">
    <team id="CLE" market="Cleveland" name="Browns" remaining_challenges="1" remaining_timeouts="2">
      <scoring points="17">
        <quarter number="1" points="0"/>
        <quarter number="2" points="17"/>
        <quarter number="3" points="0"/>
        <quarter number="4" points="0"/>
      </scoring>
    </team>
    <team id="DET" market="Detroit" name="Lions" remaining_challenges="2" remaining_timeouts="2">
      <scoring points="31">
        <quarter number="1" points="7"/>
        <quarter number="2" points="0"/>
        <quarter number="3" points="7"/>
        <quarter number="4" points="17"/>
      </scoring>
    </team>
    <scoring_drives>
      <drive clock="07:50" quarter="1" sequence="1" team="DET">
        <score clock="03:31" points="6" quarter="1" type="touchdown">
          <summary><![CDATA[9-M.Stafford complete to 80-J.Fauria. 80-J.Fauria runs 1 yard for a touchdown.]]></summary>
          <links>
            <link href="/2013/REG/6/DET/CLE/plays/0e5d364f-3dd9-4590-ab73-e8dd4910081c.xml" rel="summary" type="application/xml"/>
          </links>
        </score>
        <score clock="03:27" points="1" quarter="1" type="extrapoint">
          <summary><![CDATA[2-D.Akers extra point is good.]]></summary>
          <links>
            <link href="/2013/REG/6/DET/CLE/plays/a2fa35ca-16a4-4948-9450-aba0e5bc43e6.xml" rel="summary" type="application/xml"/>
          </links>
        </score>
      </drive>
      <drive clock="01:32" quarter="1" sequence="2" team="CLE">
        <score clock="12:57" points="6" quarter="2" type="touchdown">
          <summary><![CDATA[3-B.Weeden complete to 25-C.Ogbonnaya. 25-C.Ogbonnaya runs 4 yards for a touchdown.]]></summary>
          <links>
            <link href="/2013/REG/6/DET/CLE/plays/6dd682d8-1f6e-4255-9f30-0d7f687a60fe.xml" rel="summary" type="application/xml"/>
          </links>
        </score>
        <score clock="12:52" points="1" quarter="2" type="extrapoint">
          <summary><![CDATA[8-B.Cundiff extra point is good.]]></summary>
          <links>
            <link href="/2013/REG/6/DET/CLE/plays/03f1ec46-01d3-47fe-85ce-e54cd057c7b0.xml" rel="summary" type="application/xml"/>
          </links>
        </score>
      </drive>
      <drive clock="06:38" quarter="2" sequence="3" team="CLE">
        <score clock="01:20" points="6" quarter="2" type="touchdown">
          <summary><![CDATA[3-B.Weeden complete to 18-G.Little. 18-G.Little runs 2 yards for a touchdown.]]></summary>
          <links>
            <link href="/2013/REG/6/DET/CLE/plays/8a4daf60-4f34-479e-b1c2-47e021e0b547.xml" rel="summary" type="application/xml"/>
          </links>
        </score>
        <score clock="01:16" points="1" quarter="2" type="extrapoint">
          <summary><![CDATA[8-B.Cundiff extra point is good.]]></summary>
          <links>
            <link href="/2013/REG/6/DET/CLE/plays/825a5b30-fd24-48a6-8947-7c2da689dd9c.xml" rel="summary" type="application/xml"/>
          </links>
        </score>
      </drive>
      <drive clock=":50" quarter="2" sequence="4" team="CLE">
        <score clock=":11" points="3" quarter="2" type="fieldgoal">
          <summary><![CDATA[8-B.Cundiff 40 yards Field Goal is Good.]]></summary>
          <links>
            <link href="/2013/REG/6/DET/CLE/plays/b7b78627-c271-4a7e-b460-e113028087d5.xml" rel="summary" type="application/xml"/>
          </links>
        </score>
      </drive>
      <drive clock="12:56" quarter="3" sequence="5" team="DET">
        <score clock="09:04" points="6" quarter="3" type="touchdown">
          <summary><![CDATA[9-M.Stafford complete to 21-R.Bush. 21-R.Bush runs 18 yards for a touchdown.]]></summary>
          <links>
            <link href="/2013/REG/6/DET/CLE/plays/68281dbf-e3b0-4e59-bf17-8b9d2af7bf17.xml" rel="summary" type="application/xml"/>
          </links>
        </score>
        <score clock="08:57" points="1" quarter="3" type="extrapoint">
          <summary><![CDATA[2-D.Akers extra point is good.]]></summary>
          <links>
            <link href="/2013/REG/6/DET/CLE/plays/1ea6e0e9-ab6c-4606-809b-63e468fd5173.xml" rel="summary" type="application/xml"/>
          </links>
        </score>
      </drive>
      <drive clock="14:49" quarter="4" sequence="6" team="DET">
        <score clock="10:41" points="6" quarter="4" type="touchdown">
          <summary><![CDATA[9-M.Stafford complete to 80-J.Fauria. 80-J.Fauria runs 23 yards for a touchdown.]]></summary>
          <links>
            <link href="/2013/REG/6/DET/CLE/plays/4d1d02ae-fc36-4f5b-96d3-0d4a272805e9.xml" rel="summary" type="application/xml"/>
          </links>
        </score>
        <score clock="10:35" points="1" quarter="4" type="extrapoint">
          <summary><![CDATA[2-D.Akers extra point is good.]]></summary>
          <links>
            <link href="/2013/REG/6/DET/CLE/plays/c8d10fe6-8c07-4b33-8d03-b7addf69038d.xml" rel="summary" type="application/xml"/>
          </links>
        </score>
      </drive>
      <drive clock="08:57" quarter="4" sequence="7" team="DET">
        <score clock="06:04" points="3" quarter="4" type="fieldgoal">
          <summary><![CDATA[2-D.Akers 51 yards Field Goal is Good.]]></summary>
          <links>
            <link href="/2013/REG/6/DET/CLE/plays/191ff930-47e3-48b0-92f2-1da067e982d4.xml" rel="summary" type="application/xml"/>
          </links>
        </score>
      </drive>
      <drive clock="04:36" quarter="4" sequence="8" team="DET">
        <score clock="02:05" points="6" quarter="4" type="touchdown">
          <summary><![CDATA[9-M.Stafford complete to 80-J.Fauria. 80-J.Fauria runs 10 yards for a touchdown.]]></summary>
          <links>
            <link href="/2013/REG/6/DET/CLE/plays/b6ff7fd9-7da5-4f71-946f-e5d560060794.xml" rel="summary" type="application/xml"/>
          </links>
        </score>
        <score clock="02:01" points="1" quarter="4" type="extrapoint">
          <summary><![CDATA[2-D.Akers extra point is good.]]></summary>
          <links>
            <link href="/2013/REG/6/DET/CLE/plays/bfc371cf-f19a-41e6-9356-c0cb61c68362.xml" rel="summary" type="application/xml"/>
          </links>
        </score>
      </drive>
    </scoring_drives>
  </game>
  <game away="STL" clock=":00" completed="2013-10-13T19:48:53+00:00" home="HOU" id="2abccb3e-1a0c-4905-98fc-43f567cc975c" quarter="4" scheduled="2013-10-13T17:00:00+00:00" status="closed">
    <team id="HOU" market="Houston" name="Texans" remaining_challenges="1" remaining_timeouts="2">
      <scoring points="13">
        <quarter number="1" points="0"/>
        <quarter number="2" points="6"/>
        <quarter number="3" points="0"/>
        <quarter number="4" points="7"/>
      </scoring>
    </team>
    <team id="STL" market="St. Louis" name="Rams" remaining_challenges="2" remaining_timeouts="2">
      <scoring points="38">
        <quarter number="1" points="7"/>
        <quarter number="2" points="10"/>
        <quarter number="3" points="21"/>
        <quarter number="4" points="0"/>
      </scoring>
    </team>
    <scoring_drives>
      <drive clock="08:47" quarter="1" sequence="1" team="STL">
        <score clock="06:04" points="6" quarter="1" type="touchdown">
          <summary><![CDATA[8-S.Bradford complete to 46-C.Harkey. 46-C.Harkey runs 2 yards for a touchdown.]]></summary>
          <links>
            <link href="/2013/REG/6/STL/HOU/plays/5b4a81fc-f254-421f-92e0-098fd54b9120.xml" rel="summary" type="application/xml"/>
          </links>
        </score>
        <score clock="05:59" points="1" quarter="1" type="extrapoint">
          <summary><![CDATA[4-G.Zuerlein extra point is good.]]></summary>
          <links>
            <link href="/2013/REG/6/STL/HOU/plays/990ef97e-8842-49ed-bbe1-5f679df8f622.xml" rel="summary" type="application/xml"/>
          </links>
        </score>
      </drive>
      <drive clock="01:44" quarter="1" sequence="2" team="STL">
        <score clock="13:25" points="3" quarter="2" type="fieldgoal">
          <summary><![CDATA[4-G.Zuerlein 42 yards Field Goal is Good.]]></summary>
          <links>
            <link href="/2013/REG/6/STL/HOU/plays/a8f876c7-4d35-4d94-bcf7-d953418a1cef.xml" rel="summary" type="application/xml"/>
          </links>
        </score>
      </drive>
      <drive clock="13:22" quarter="2" sequence="3" team="HOU">
        <score clock="08:23" points="3" quarter="2" type="fieldgoal">
          <summary><![CDATA[4-R.Bullock 20 yards Field Goal is Good.]]></summary>
          <links>
            <link href="/2013/REG/6/STL/HOU/plays/96a2ab88-1604-466f-ab5d-668e7ddd6378.xml" rel="summary" type="application/xml"/>
          </links>
        </score>
      </drive>
      <drive clock="08:21" quarter="2" sequence="4" team="STL">
        <score clock="02:48" points="6" quarter="2" type="touchdown">
          <summary><![CDATA[8-S.Bradford complete to 88-L.Kendricks. 88-L.Kendricks runs 2 yards for a touchdown.]]></summary>
          <links>
            <link href="/2013/REG/6/STL/HOU/plays/e0d1a492-9cfa-4ce0-83f4-dee03607c1c6.xml" rel="summary" type="application/xml"/>
          </links>
        </score>
        <score clock="02:43" points="1" quarter="2" type="extrapoint">
          <summary><![CDATA[4-G.Zuerlein extra point is good.]]></summary>
          <links>
            <link href="/2013/REG/6/STL/HOU/plays/00853a76-ea42-46f8-981b-26857ee9911a.xml" rel="summary" type="application/xml"/>
          </links>
        </score>
      </drive>
      <drive clock="02:43" quarter="2" sequence="5" team="HOU">
        <score clock=":53" points="3" quarter="2" type="fieldgoal">
          <summary><![CDATA[4-R.Bullock 35 yards Field Goal is Good.]]></summary>
          <links>
            <link href="/2013/REG/6/STL/HOU/plays/49da75e1-6cfc-46d3-8891-2c7c25bcedcc.xml" rel="summary" type="application/xml"/>
          </links>
        </score>
      </drive>
      <drive clock="13:02" quarter="3" sequence="6" team="STL">
        <score clock="07:46" points="6" quarter="3" type="touchdown">
          <summary><![CDATA[8-S.Bradford complete to 83-B.Quick. 83-B.Quick runs 4 yards for a touchdown.]]></summary>
          <links>
            <link href="/2013/REG/6/STL/HOU/plays/e5a643a1-c0bf-4f98-a934-183c44d40d2f.xml" rel="summary" type="application/xml"/>
          </links>
        </score>
        <score clock="07:42" points="1" quarter="3" type="extrapoint">
          <summary><![CDATA[4-G.Zuerlein extra point is good.]]></summary>
          <links>
            <link href="/2013/REG/6/STL/HOU/plays/b4d573f5-6680-4976-9f34-f212344f80cc.xml" rel="summary" type="application/xml"/>
          </links>
        </score>
      </drive>
      <drive clock="07:42" quarter="3" sequence="7" team="HOU">
        <score clock="07:42" points="6" quarter="3" type="touchdown">
          <summary><![CDATA[4-G.Zuerlein kicks 70 yards from STL 35. 82-K.Martin to HOU 10, FUMBLES (23-R.McLeod). 53-D.Bates runs 11 yards for a touchdown.]]></summary>
          <links>
            <link href="/2013/REG/6/STL/HOU/plays/626d7d15-94a7-4324-b923-4caf264eabe1.xml" rel="summary" type="application/xml"/>
          </links>
        </score>
      </drive>
      <drive clock="07:36" quarter="3" sequence="8" team="STL">
        <score clock="07:36" points="1" quarter="3" type="extrapoint">
          <summary><![CDATA[4-G.Zuerlein extra point is good.]]></summary>
          <links>
            <link href="/2013/REG/6/STL/HOU/plays/0971dd91-2820-400c-a141-4124fd25d2db.xml" rel="summary" type="application/xml"/>
          </links>
        </score>
      </drive>
      <drive clock="07:36" quarter="3" sequence="9" team="HOU">
        <score clock=":52" points="6" quarter="3" type="touchdown">
          <summary><![CDATA[13-T.Yates incomplete. Intended for 88-G.Graham, INTERCEPTED by 52-A.Ogletree at STL 2. 52-A.Ogletree runs 98 yards for a touchdown.]]></summary>
          <links>
            <link href="/2013/REG/6/STL/HOU/plays/d255e78b-8107-4cee-b656-927317c5ae8a.xml" rel="summary" type="application/xml"/>
          </links>
        </score>
      </drive>
      <drive clock=":36" quarter="3" sequence="10" team="STL">
        <score clock=":36" points="1" quarter="3" type="extrapoint">
          <summary><![CDATA[4-G.Zuerlein extra point is good.]]></summary>
          <links>
            <link href="/2013/REG/6/STL/HOU/plays/5f0f8b1f-e2bb-4ef1-84c2-f326cc591f2c.xml" rel="summary" type="application/xml"/>
          </links>
        </score>
      </drive>
      <drive clock="09:17" quarter="4" sequence="11" team="HOU">
        <score clock="03:25" points="6" quarter="4" type="touchdown">
          <summary><![CDATA[44-B.Tate runs 1 yard for a touchdown.]]></summary>
          <links>
            <link href="/2013/REG/6/STL/HOU/plays/8e858103-8fa5-4e5e-a93a-d76ac82a471f.xml" rel="summary" type="application/xml"/>
          </links>
        </score>
        <score clock="03:15" points="1" quarter="4" type="extrapoint">
          <summary><![CDATA[4-R.Bullock extra point is good.]]></summary>
          <links>
            <link href="/2013/REG/6/STL/HOU/plays/5920545e-90cd-4264-b5b8-339e8058d352.xml" rel="summary" type="application/xml"/>
          </links>
        </score>
      </drive>
    </scoring_drives>
  </game>
  <game away="NO" clock=":00" completed="2013-10-13T23:40:59+00:00" home="NE" id="e76450a1-a8df-46f6-96dc-6416dbfa03fe" quarter="4" scheduled="2013-10-13T20:25:00+00:00" status="closed">
    <team id="NE" market="New England" name="Patriots" remaining_challenges="2" remaining_timeouts="2">
      <scoring points="30">
        <quarter number="1" points="3"/>
        <quarter number="2" points="14"/>
        <quarter number="3" points="3"/>
        <quarter number="4" points="10"/>
      </scoring>
    </team>
    <team id="NO" market="New Orleans" name="Saints" remaining_challenges="2" remaining_timeouts="2">
      <scoring points="27">
        <quarter number="1" points="7"/>
        <quarter number="2" points="0"/>
        <quarter number="3" points="10"/>
        <quarter number="4" points="10"/>
      </scoring>
    </team>
    <scoring_drives>
      <drive clock="15:00" quarter="1" sequence="1" team="NE">
        <score clock="09:58" points="3" quarter="1" type="fieldgoal">
          <summary><![CDATA[3-S.Gostkowski 35 yards Field Goal is Good.]]></summary>
          <links>
            <link href="/2013/REG/6/NO/NE/plays/8adbae43-8804-4cbb-b0a7-83dd003b21af.xml" rel="summary" type="application/xml"/>
          </links>
        </score>
      </drive>
      <drive clock="07:09" quarter="1" sequence="2" team="NO">
        <score clock="01:51" points="6" quarter="1" type="touchdown">
          <summary><![CDATA[9-D.Brees complete to 39-T.Cadet. 39-T.Cadet runs 3 yards for a touchdown.]]></summary>
          <links>
            <link href="/2013/REG/6/NO/NE/plays/0a9f20e1-41f8-4247-8a9b-08244f4cf6a1.xml" rel="summary" type="application/xml"/>
          </links>
        </score>
        <score clock="01:46" points="1" quarter="1" type="extrapoint">
          <summary><![CDATA[5-G.Hartley extra point is good.]]></summary>
          <links>
            <link href="/2013/REG/6/NO/NE/plays/edc32f63-da0b-44ee-a8af-2214588ddd9d.xml" rel="summary" type="application/xml"/>
          </links>
        </score>
      </drive>
      <drive clock="01:46" quarter="1" sequence="3" team="NE">
        <score clock="13:02" points="6" quarter="2" type="touchdown">
          <summary><![CDATA[22-S.Ridley runs 1 yard for a touchdown.]]></summary>
          <links>
            <link href="/2013/REG/6/NO/NE/plays/a7793bf0-a73b-481f-be63-669fd45570aa.xml" rel="summary" type="application/xml"/>
          </links>
        </score>
        <score clock="13:00" points="1" quarter="2" type="extrapoint">
          <summary><![CDATA[3-S.Gostkowski extra point is good.]]></summary>
          <links>
            <link href="/2013/REG/6/NO/NE/plays/a4349671-97ac-4c28-a96b-56c9aabe0d35.xml" rel="summary" type="application/xml"/>
          </links>
        </score>
      </drive>
      <drive clock="12:28" quarter="2" sequence="4" team="NE">
        <score clock="07:40" points="6" quarter="2" type="touchdown">
          <summary><![CDATA[22-S.Ridley runs 4 yards for a touchdown.]]></summary>
          <links>
            <link href="/2013/REG/6/NO/NE/plays/7f97f211-3928-4cd2-9efe-2caba47f6ba8.xml" rel="summary" type="application/xml"/>
          </links>
        </score>
        <score clock="07:36" points="1" quarter="2" type="extrapoint">
          <summary><![CDATA[3-S.Gostkowski extra point is good.]]></summary>
          <links>
            <link href="/2013/REG/6/NO/NE/plays/7117a009-28c3-4151-8911-d83acbaf33d4.xml" rel="summary" type="application/xml"/>
          </links>
        </score>
      </drive>
      <drive clock="15:00" quarter="3" sequence="5" team="NO">
        <score clock="11:31" points="3" quarter="3" type="fieldgoal">
          <summary><![CDATA[5-G.Hartley 28 yards Field Goal is Good.]]></summary>
          <links>
            <link href="/2013/REG/6/NO/NE/plays/3ab1144c-f33d-4f58-9647-f4a21754cc8c.xml" rel="summary" type="application/xml"/>
          </links>
        </score>
      </drive>
      <drive clock="10:26" quarter="3" sequence="6" team="NO">
        <score clock="06:23" points="6" quarter="3" type="touchdown">
          <summary><![CDATA[29-K.Robinson runs 3 yards for a touchdown.]]></summary>
          <links>
            <link href="/2013/REG/6/NO/NE/plays/fcfb8ecc-e7a0-409b-b087-f924c22e0727.xml" rel="summary" type="application/xml"/>
          </links>
        </score>
        <score clock="06:19" points="1" quarter="3" type="extrapoint">
          <summary><![CDATA[5-G.Hartley extra point is good.]]></summary>
          <links>
            <link href="/2013/REG/6/NO/NE/plays/39c193a4-7020-4e86-bc2e-b096faa14e3b.xml" rel="summary" type="application/xml"/>
          </links>
        </score>
      </drive>
      <drive clock="06:19" quarter="3" sequence="7" team="NE">
        <score clock="01:42" points="3" quarter="3" type="fieldgoal">
          <summary><![CDATA[3-S.Gostkowski 54 yards Field Goal is Good.]]></summary>
          <links>
            <link href="/2013/REG/6/NO/NE/plays/08622f7d-de5e-4962-91d2-a6e49b1a61ba.xml" rel="summary" type="application/xml"/>
          </links>
        </score>
      </drive>
      <drive clock="12:10" quarter="4" sequence="8" team="NE">
        <score clock="08:37" points="3" quarter="4" type="fieldgoal">
          <summary><![CDATA[3-S.Gostkowski 23 yards Field Goal is Good.]]></summary>
          <links>
            <link href="/2013/REG/6/NO/NE/plays/529a01cb-a8a2-4479-a50a-32707ef1b8af.xml" rel="summary" type="application/xml"/>
          </links>
        </score>
      </drive>
      <drive clock="08:34" quarter="4" sequence="9" team="NO">
        <score clock="03:35" points="6" quarter="4" type="touchdown">
          <summary><![CDATA[9-D.Brees complete to 84-K.Stills. 84-K.Stills runs 34 yards for a touchdown.]]></summary>
          <links>
            <link href="/2013/REG/6/NO/NE/plays/5984321d-1d11-433a-aa7c-852091ddf2c8.xml" rel="summary" type="application/xml"/>
          </links>
        </score>
        <score clock="03:29" points="1" quarter="4" type="extrapoint">
          <summary><![CDATA[5-G.Hartley extra point is good.]]></summary>
          <links>
            <link href="/2013/REG/6/NO/NE/plays/57f2bf17-0a92-4e0c-bf5c-170b4b54a3ac.xml" rel="summary" type="application/xml"/>
          </links>
        </score>
      </drive>
      <drive clock="02:46" quarter="4" sequence="10" team="NO">
        <score clock="02:29" points="3" quarter="4" type="fieldgoal">
          <summary><![CDATA[5-G.Hartley 39 yards Field Goal is Good.]]></summary>
          <links>
            <link href="/2013/REG/6/NO/NE/plays/3602dcb9-333e-4116-bb07-10121cc39962.xml" rel="summary" type="application/xml"/>
          </links>
        </score>
      </drive>
      <drive clock="01:13" quarter="4" sequence="11" team="NE">
        <score clock=":10" points="6" quarter="4" type="touchdown">
          <summary><![CDATA[12-T.Brady complete to 85-K.Thompkins. 85-K.Thompkins runs 17 yards for a touchdown.]]></summary>
          <links>
            <link href="/2013/REG/6/NO/NE/plays/236a4ee8-52b0-4fc7-9f6a-d9d32535203f.xml" rel="summary" type="application/xml"/>
          </links>
        </score>
        <score clock=":05" points="1" quarter="4" type="extrapoint">
          <summary><![CDATA[3-S.Gostkowski extra point is good.]]></summary>
          <links>
            <link href="/2013/REG/6/NO/NE/plays/84a4bcc6-d46e-43ce-a766-b0e4b0d67980.xml" rel="summary" type="application/xml"/>
          </links>
        </score>
      </drive>
    </scoring_drives>
  </game>
<!--Generation finished at 2014-08-27 20:26:58 +0000--></games>
